Workbook

Sheet 00_Executive_Dashboard
A1: VN-INDEX QUANTITATIVE SCORING SYSTEM — EXECUTIVE DASHBOARD
A2: Institutional quarterly macro-quant model | formula-driven | point-in-time inputs | 2021-Q1 to latest available quarter
A5: LATEST QUARTER | B5: CALIBRATED ACTION | C5: CALIBRATED SCORE | D5: EQUITY ALLOCATION | E5: RAW COMPOSITE
A6: =INDEX('05_Composite_Calibration'!A5:A28,COUNTA('05_Composite_Calibration'!A5:A28)) | B6: =INDEX('05_Composite_Calibration'!K5:K28,COUNTA('05_Composite_Calibration'!A5:A28)) | C6: =INDEX('05_Composite_Calibration'!J5:J28,COUNTA('05_Composite_Calibration'!A5:A28)) | D6: =INDEX('05_Composite_Calibration'!L5:L28,COUNTA('05_Composite_Calibration'!A5:A28)) | E6: =INDEX('05_Composite_Calibration'!D5:D28,COUNTA('05_Composite_Calibration'!A5:A28))
A9: LATEST-QUARTER SIX-PILLAR DECOMPOSITION
A10: Pillar | B10: Weight | C10: Raw Score | D10: Weighted Contribution | E10: % of Composite | F10: Assessment
A11: Macro & Monetary | B11: ='01_Model_Config'!C6 | C11: =INDEX('04_Pillar_Calculation'!C5:C28,COUNTA('04_Pillar_Calculation'!A5:A28)) | D11: =INDEX('04_Pillar_Calculation'!K5:K28,COUNTA('04_Pillar_Calculation'!A5:A28)) | E11: =D11/$D$17 | F11: =IF(C11>=65,"Favorable",IF(C11>=50,"Neutral","Unfavorable"))
A12: Global & Intermarket | B12: ='01_Model_Config'!C7 | C12: =INDEX('04_Pillar_Calculation'!D5:D28,COUNTA('04_Pillar_Calculation'!A5:A28)) | D12: =INDEX('04_Pillar_Calculation'!L5:L28,COUNTA('04_Pillar_Calculation'!A5:A28)) | E12: =D12/$D$17 | F12: =IF(C12>=65,"Favorable",IF(C12>=50,"Neutral","Unfavorable"))
A13: Valuation & Leverage | B13: ='01_Model_Config'!C8 | C13: =INDEX('04_Pillar_Calculation'!E5:E28,COUNTA('04_Pillar_Calculation'!A5:A28)) | D13: =INDEX('04_Pillar_Calculation'!M5:M28,COUNTA('04_Pillar_Calculation'!A5:A28)) | E13: =D13/$D$17 | F13: =IF(C13>=65,"Favorable",IF(C13>=50,"Neutral","Unfavorable"))
A14: Econometric Models | B14: ='01_Model_Config'!C9 | C14: =INDEX('04_Pillar_Calculation'!F5:F28,COUNTA('04_Pillar_Calculation'!A5:A28)) | D14: =INDEX('04_Pillar_Calculation'!N5:N28,COUNTA('04_Pillar_Calculation'!A5:A28)) | E14: =D14/$D$17 | F14: =IF(C14>=65,"Favorable",IF(C14>=50,"Neutral","Unfavorable"))
A15: Machine Learning | B15: ='01_Model_Config'!C10 | C15: =INDEX('04_Pillar_Calculation'!G5:G28,COUNTA('04_Pillar_Calculation'!A5:A28)) | D15: =INDEX('04_Pillar_Calculation'!O5:O28,COUNTA('04_Pillar_Calculation'!A5:A28)) | E15: =D15/$D$17 | F15: =IF(C15>=65,"Favorable",IF(C15>=50,"Neutral","Unfavorable"))
A16: Market Structure | B16: ='01_Model_Config'!C11 | C16: =INDEX('04_Pillar_Calculation'!H5:H28,COUNTA('04_Pillar_Calculation'!A5:A28)) | D16: =INDEX('04_Pillar_Calculation'!P5:P28,COUNTA('04_Pillar_Calculation'!A5:A28)) | E16: =D16/$D$17 | F16: =IF(C16>=65,"Favorable",IF(C16>=50,"Neutral","Unfavorable"))
A17: COMPOSITE TOTAL | B17: =SUM(B11:B16) | C17: =SUMPRODUCT(B11:B16,C11:C16) | D17: =SUM(D11:D16) | E17: =SUM(E11:E16) | F17: =INDEX('05_Composite_Calibration'!E5:E28,COUNTA('05_Composite_Calibration'!A5:A28))
A20: BACKTEST & SIGNAL EFFICACY SUMMARY
A21: Metric | B21: Formula Result | C21: Acceptance Reference | D21: Interpretation
A22: Strategy CAGR | B22: ='10_Backtest_Efficacy'!B33 | C22: ≈ 5.74% | D22: Annualized dashboard-compatible strategy return
A23: Maximum Drawdown | B23: ='10_Backtest_Efficacy'!B34 | C23: ≈ -9.02% | D23: Worst peak-to-trough strategy decline
A24: Annualized Volatility | B24: ='10_Backtest_Efficacy'!B35 | C24: ≈ 7.70% | D24: Quarterly volatility annualized by √4
A25: Sharpe Ratio | B25: ='10_Backtest_Efficacy'!B36 | C25: ≈ 0.16 | D25: CAGR less configured risk-free rate, divided by volatility
A26: Spearman Rank IC | B26: ='10_Backtest_Efficacy'!B37 | C26: ≈ 0.1927 | D26: Raw score rank vs strict point-in-time quarter return rank
A27: Directional Hit Rate | B27: ='10_Backtest_Efficacy'!B38 | C27: Formula | D27: Action-direction agreement with dashboard forward return

Sheet 01_Model_Config
A1: VN-INDEX MODEL CONFIGURATION — SINGLE SOURCE OF TRUTH
A2: Weights, score bands, calibration parameters, signal gains and backtest assumptions
A4: 1. PILLAR WEIGHTS
A5: Pillar Code | B5: Pillar Name | C5: Weight | D5: Primary Inputs
A6: macro_monetary | B6: Macro & Monetary | C6: 0.25 | D6: Rates, FX, M2 and sovereign curve
A7: global_intermarket | B7: Global & Intermarket | C7: 0.2 | D7: DXY, US10Y, foreign flows, JPY and oil
A8: valuation_leverage | B8: Valuation & Leverage | C8: 0.2 | D8: P/E, P/B, EYG and margin risk
A9: quant_model | B9: Econometric Models | C9: 0.15 | D9: MLR, VAR and Granger causality
A10: ml_forecast | B10: Machine Learning | C10: 0.1 | D10: XGBoost walk-forward quality and signal
A11: market_structure | B11: Market Structure | C11: 0.1 | D11: FTSE, ADTV and ETF flows
A12: TOTAL WEIGHT | C12: =SUM(C6:C11) | D12: Must equal 100%
A14: 2. SCORE BANDS & ALLOCATION MATRIX
A15: Minimum | B15: Maximum | C15: Action | D15: Emoji | E15: Suggested Allocation | F15: Model Mid-Weight | G15: Risk Posture
A16: 80 | B16: 100 | C16: BUY | D16: 🟢 | E16: 85–100% Equities | F16: 0.925 | G16: Aggressive risk-on
A17: 65 | B17: 79.9999 | C17: ACCUMULATE | D17: 🔵 | E17: 70–85% Equities | F17: 0.775 | G17: Constructive risk-on
A18: 50 | B18: 64.9999 | C18: HOLD | D18: 🟡 | E18: 40–60% Equities | F18: 0.5 | G18: Balanced / neutral
A19: 35 | B19: 49.9999 | C19: REDUCE | D19: 🟠 | E19: 20–40% Equities | F19: 0.3 | G19: Defensive
A20: 0 | B20: 34.9999 | C20: SELL | D20: 🔴 | E20: 0–20% Equities | F20: 0.1 | G20: Capital preservation
A22: 3. EXPANDING CALIBRATION PARAMETERS (v2 — winsorized, guard-railed)
A23: Parameter | B23: Value | C23: Role
A24: center | B24: 50 | C24: Calibrated-score center
A25: z_scale | B25: 15 | C25: Points per historical σ
A26: min_history | B26: 4 | C26: Required prior quarters
A27: clip_low | B27: 0 | C27: Score floor
A28: clip_high | B28: 100 | C28: Score cap
A30: 4. MODEL GAINS & BACKTEST ASSUMPTIONS
A31: Parameter | B31: Value | C31: Formula / Interpretation
A32: MLR gain | B32: 20000 | C32: 50 + forecast/day × gain
A33: VAR gain | B33: 5000 | C33: 50 + T+5 return × gain
A34: Periods per year | B34: 4 | C34: Quarterly annualization
A35: Initial NAV | B35: 100 | C35: Strategy and benchmark base
A36: Risk-free rate | B36: 0.045 | C36: Annual Sharpe hurdle
A38: 5. CALIBRATION v2 ROBUSTNESS GUARDS
A39: Parameter | B39: Value | C39: Role
A40: min_std | B40: 5 | C40: σ prior floor: tiny-sample σ cannot inflate z (floor ≈ long-run composite dispersion)
A41: z_cap | B41: 3 | C41: Winsorise z at ±3σ → response saturates near 5/95; 0/100 unreachable
A42: max_dist_from_raw | B42: 25 | C42: Action signal may not deviate more than ±25 pts from the raw composite

Sheet 02_Market_Inputs
A1: POINT-IN-TIME MARKET & MODEL INPUT LEDGER
A2: Every Quarter t input is dated at the last available session of t−1; the separate outcome close is never used in scoring
A4: Quarter | B4: As-of Date | C4: As-of VN-Index Close | D4: Quarter-End Outcome Close | E4: VN1Y % | F4: ΔVN1Y pp | G4: VN10Y % | H4: Spread pp | I4: USD/VND Z | J4: M2 YoY % | K4: DXY Z | L4: US10Y % | M4: NFF Z | N4: NFF % MC | O4: USD/JPY Z | P4: Oil Shock | Q4: P/E Z | R4: P/B Z | S4: Margin Risk | T4: EYG Z | U4: Valuation Composite | V4: ADTV QoQ | W4: FTSE Status | X4: Months to Rebal | Y4: ETF Flow Z | Z4: ETF % MC
A5: 2021-Q1 | B5: 2020-12-31 | C5: 1103.87 | D5: 1191.44 | E5: 0.4326 | F5: -0.064174 | G5: 2.0246 | H5: 1.3872 | I5: -2.68 | J5: 14.53 | K5: -1.57 | L5: 0.92 | M5: -2.4315 | N5: -0.4358 | O5: -1.76 | P5: 20.7 | S5: 0 | V5: 0.606722 | W5: unknown | X5: 3 | Y5: 1.8116 | Z5: 0.0559
A6: 2021-Q2 | B6: 2021-03-31 | C6: 1191.44 | D6: 1408.55 | E6: 0.464 | F6: -0.013805 | G6: 2.2209 | H6: 1.669 | I6: 0.6 | J6: 14.53 | K6: 2.39 | L6: 1.75 | M6: -4.0648 | N6: -0.9813 | O6: 1.95 | P6: 19.9 | S6: 4 | V6: 0.422295 | W6: unknown | X6: 3 | Y6: 5.9155 | Z6: 0.1566
A7: 2021-Q3 | B7: 2021-06-30 | C7: 1408.55 | D7: 1342.06 | E7: 0.5013 | F7: 0.001505 | G7: 2.057 | H7: 1.3519 | I7: 0.18 | J7: 14.53 | K7: 1.96 | L7: 1.44 | M7: -0.5589 | N7: -0.3302 | O7: 1.5 | P7: 12 | S7: 0 | V7: 0.111991 | W7: unknown | X7: 3 | Y7: 0.4047 | Z7: 0.0557
A8: 2021-Q4 | B8: 2021-09-30 | C8: 1342.06 | D8: 1498.28 | E8: 0.5017 | F8: 0.001321 | G8: 1.9128 | H8: 1.2312 | I8: -0.65 | J8: 14.53 | K8: 2.89 | L8: 1.53 | M8: 0.0507 | N8: -0.1213 | O8: 3.84 | P8: 21.8 | S8: 15 | V8: -0.063721 | W8: unknown | X8: 3 | Y8: -1.5849 | Z8: -0.0332
A9: 2022-Q1 | B9: 2021-12-31 | C9: 1498.28 | D9: 1492.15 | E9: 0.4944 | F9: 0.017019 | G9: 2.007 | H9: 1.4797 | I9: -0.05 | J9: 10.66 | K9: 0.33 | L9: 1.51 | M9: -0.4292 | N9: -0.286 | O9: 1.82 | P9: 19.1 | Q9: 1.3716286 | R9: 1.724412 | S9: 1 | T9: -0.89270763 | V9: 0.33276 | W9: unknown | X9: 3 | Y9: -0.3814 | Z9: 0.0142
A10: 2022-Q2 | B10: 2022-03-31 | C10: 1492.15 | D10: 1197.6 | E10: 1.3143 | F10: -0.060524 | G10: 2.424 | H10: 0.9445 | I10: 1.02 | J10: 10.66 | K10: 1.03 | L10: 2.33 | M10: 0.1512 | N10: -0.0992 | O10: 2.24 | P10: 43.6 | Q10: 1.2473397 | R10: 1.5929063 | S10: 11 | T10: -0.85124281 | V10: -0.076852 | W10: unknown | X10: 3 | Y10: -0.7594 | Z10: -0.0039
A11: 2022-Q3 | B11: 2022-06-30 | C11: 1197.6 | D11: 1132.11 | E11: 1.8151 | F11: -0.005296 | G11: 3.2011 | H11: 1.1263 | I11: 1.35 | J11: 10.66 | K11: 1.18 | L11: 2.97 | M11: 0.6204 | N11: 0.0525 | O11: 1.87 | P11: 21.1 | Q11: 0.0061852326 | R11: -0.12402402 | S11: 80 | T11: -0.39697033 | V11: -0.295489 | W11: unknown | X11: 3 | Y11: 0.4218 | Z11: 0.0476
A12: 2022-Q4 | B12: 2022-09-30 | C12: 1132.11 | D12: 1007.09 | E12: 4.0572 | F12: 0.202285 | G12: 4.674 | H12: 0.5962 | I12: 2.82 | J12: 10.66 | K12: 1.68 | L12: 3.8 | M12: 0.5065 | N12: 0.0255 | O12: 1.52 | P12: 17.4 | Q12: -0.21260386 | R12: -0.41728564 | S12: 54 | T12: -0.42088188 | V12: -0.087319 | W12: unknown | X12: 3 | Y12: -1.4748 | Z12: -0.0348
A13: 2023-Q1 | B13: 2022-12-30 | C13: 1007.09 | D13: 1064.64 | E13: 4.6775 | F13: -0.03116 | G13: 4.8245 | H13: 0.1576 | I13: -1.39 | J13: 10.66 | K13: -1.29 | L13: 3.88 | M13: 2.1533 | N13: 0.5325 | O13: -1.44 | P13: 22 | Q13: -0.69468194 | R13: -1.0494135 | S13: 35 | T13: -0.049359684 | V13: 0.192768 | W13: unknown | X13: 3 | Y13: 0.6843 | Z13: 0.0567
A14: 2023-Q2 | B14: 2023-03-31 | C14: 1064.64 | D14: 1120.18 | E14: 3.3908 | F14: -0.068954 | G14: 3.5545 | H14: 0.1561 | I14: -0.76 | J14: 6.15 | K14: -0.72 | L14: 3.49 | M14: 0.5327 | N14: 0.0941 | O14: 0.32 | P14: 17.3 | Q14: -0.48426225 | R14: -0.74706526 | S14: 21 | T14: -0.0075394935 | V14: -0.191478 | W14: unknown | X14: 3 | Y14: -0.24 | Z14: 0.0169
A15: 2023-Q3 | B15: 2023-06-30 | C15: 1120.18 | D15: 1154.15 | E15: 2.1614 | F15: -0.006956 | G15: 2.5684 | H15: 0.3695 | I15: 2.97 | J15: 6.15 | K15: 0.3 | L15: 3.82 | M15: -0.124 | N15: -0.1149 | O15: 2.05 | P15: 17.1 | Q15: 0.055005503 | R15: -0.10455154 | S15: 7 | T15: -0.21206364 | V15: 0.399685 | W15: unknown | X15: 3 | Y15: -0.7902 | Z15: -0.0072
A16: 2023-Q4 | B16: 2023-09-29 | C16: 1154.15 | D16: 1129.93 | E16: 1.868 | F16: 0.029032 | G16: 2.4762 | H16: 0.5369 | I16: 1.82 | J16: 6.15 | K16: 1.57 | L16: 4.57 | M16: 0.0585 | N16: -0.0579 | O16: 1.48 | P16: 13.5 | Q16: 0.34176328 | R16: 0.36886409 | S16: 33 | T16: -0.34595104 | V16: 0.288734 | W16: unknown | X16: 3 | Y16: -1.4875 | Z16: -0.0384
A17: 2024-Q1 | B17: 2023-12-29 | C17: 1129.93 | D17: 1284.09 | E17: 1.6115 | F17: 0.010374 | G17: 2.2174 | H17: 0.5376 | I17: -0.96 | J17: 6.15 | K17: -1.73 | L17: 3.87 | M17: -0.2633 | N17: -0.1571 | O17: -2.03 | P17: 14.8 | Q17: 0.42314624 | R17: 0.39293487 | S17: 10 | T17: -0.33528921 | V17: -0.288754 | W17: unknown | X17: 3 | Y17: -1.7808 | Z17: -0.0563
A18: 2024-Q2 | B18: 2024-03-29 | C18: 1284.09 | D18: 1245.32 | E18: 1.5461 | F18: 0.022309 | G18: 2.4651 | H18: 0.8931 | I18: 1.68 | J18: 12.46 | K18: 1.38 | L18: 4.21 | M18: -0.0101 | N18: -0.0825 | O18: 1.39 | P18: 12 | Q18: 1.1112195 | R18: 1.255887 | S18: 2 | T18: -0.66956951 | V18: 0.260258 | W18: unknown | X18: 3 | Y18: -1.7549 | Z18: -0.0627
A19: 2024-Q3 | B19: 2024-06-28 | C19: 1245.32 | D19: 1287.94 | E19: 2.0678 | F19: 0.0517 | G19: 2.7738 | H19: 0.6057 | I19: 0.56 | J19: 12.46 | K19: 1.03 | L19: 4.34 | M19: -0.919 | N19: -0.3509 | O19: 2.26 | P19: 9 | Q19: 1.2951725 | R19: 1.4665091 | S19: 19 | T19: -0.78549701 | V19: -0.070967 | W19: unknown | X19: 3 | Y19: -2.04 | Z19: -0.0838
A20: 2024-Q4 | B20: 2024-09-30 | C20: 1287.94 | D20: 1266.78 | E20: 1.8875 | F20: -0.044628 | G20: 2.8461 | H20: 0.8262 | I20: -1.33 | J20: 12.46 | K20: -1.09 | L20: 3.8 | M20: -0.2976 | N20: -0.1789 | O20: -0.92 | P20: 13.3 | Q20: 1.2345458 | R20: 1.3854181 | S20: 2 | T20: -0.77529072 | V20: -0.22597 | W20: unknown | X20: 3 | Y20: -0.3091 | Z20: -0.0056
... A28: 2026-Q4 | B28: 2026-09-30 | C28: 1768.62 | D28: 1749.3 | E28: 3.8244862 | F28: -0.006669987 | G28: 4.4903384 | H28: 0.56417624 | I28: -1.2884 | J28: 14.98 | K28: 1.5610034 | L28: 5.2930002 | M28: -0.12209485 | N28: -0.18012223 | O28: -0.5758619 | P28: 43.812594 | Q28: 0.75094412 | R28: 0.63804465 | S28: 20.398842 | T28: -1.2227083 | V28: -0.12261541 | W28: confirmed | X28: 3 | Y28: -0.11475527 | Z28: 0.0013040779

Sheet 03_Factor_SubScores
A1: FORMULA-NORMALIZED FACTOR SUB-SCORES
A2: All 0–100 factor scores are live formulas sourced from the point-in-time input and model ledgers
A4: Quarter | B4: As-of Date | C4: VN1Y | D4: IR Trend | E4: FX | F4: M2 | G4: VN Bonds | H4: DXY | I4: US10Y | J4: NFF | K4: JPY Carry | L4: Oil Shock | M4: P/E | N4: P/B | O4: Margin | P4: EYG | Q4: MLR Signal | R4: VAR Signal | S4: ML Quality | T4: ML Direction | U4: FTSE + Rebal | V4: ADTV | W4: ETF Flow
A5: ='02_Market_Inputs'!A5 | B5: ='02_Market_Inputs'!B5 | C5: =IF(ISBLANK('02_Market_Inputs'!E5),50,MIN(100,MAX(0,100-('02_Market_Inputs'!E5-1)*14))) | D5: =IF(ISBLANK('02_Market_Inputs'!F5),50,MIN(100,MAX(0,50-'02_Market_Inputs'!F5*100))) | E5: =IF(ISBLANK('02_Market_Inputs'!I5),50,MIN(100,MAX(0,50-'02_Market_Inputs'!I5*15))) | F5: =IF(ISBLANK('02_Market_Inputs'!J5),50,MIN(100,MAX(0,80-ABS('02_Market_Inputs'!J5-12)*4))) | G5: =IF(OR(ISBLANK('02_Market_Inputs'!G5),ISBLANK('02_Market_Inputs'!H5)),50,(MIN(100,MAX(0,100-('02_Market_Inputs'!G5-2.5)*28.5))+MIN(100,MAX(0,('02_Market_Inputs'!H5+0.2)*58)))/2) | H5: =IF(ISBLANK('02_Market_Inputs'!K5),50,MIN(100,MAX(0,50-'02_Market_Inputs'!K5*20))) | I5: =IF(ISBLANK('02_Market_Inputs'!L5),50,MIN(100,MAX(0,100-'02_Market_Inputs'!L5*20))) | J5: =IF(ISBLANK('02_Market_Inputs'!M5),50,MIN(100,MAX(0,50+'02_Market_Inputs'!M5*15))) | K5: =IF(ISBLANK('02_Market_Inputs'!O5),50,MIN(100,MAX(0,50+'02_Market_Inputs'!O5*15))) | L5: =IF(OR(ISBLANK('02_Market_Inputs'!P5),'02_Market_Inputs'!P5<=0),50,MIN(100,MAX(0,100-'02_Market_Inputs'!P5))) | M5: =IF(ISBLANK('02_Market_Inputs'!Q5),50,MIN(100,MAX(0,50-'02_Market_Inputs'!Q5*25))) | N5: =IF(ISBLANK('02_Market_Inputs'!R5),50,MIN(100,MAX(0,50-'02_Market_Inputs'!R5*25))) | O5: =IF(ISBLANK('02_Market_Inputs'!S5),50,MIN(100,MAX(0,100-'02_Market_Inputs'!S5))) | P5: =IF(ISBLANK('02_Market_Inputs'!T5),50,MIN(100,MAX(0,50+'02_Market_Inputs'!T5*25))) | Q5: ='06_MLR_Regression'!H5 | R5: ='07_VAR_Granger'!K5 | S5: ='08_ML_Validation'!K5 | T5: ='08_ML_Validation'!L5 | U5: =IF('02_Market_Inputs'!W5="completed",85,IF('02_Market_Inputs'!W5="confirmed",75,IF('02_Market_Inputs'!W5="pending",55,50)))+IF('02_Market_Inputs'!X5<=1,20,IF('02_Market_Inputs'!X5<=2,12,IF('02_Market_Inputs'!X5<=3,6,0))) | V5: =IF(ISBLANK('02_Market_Inputs'!V5),50,MIN(100,MAX(0,50+'02_Market_Inputs'!V5*100))) | W5: =IF(ISBLANK('02_Market_Inputs'!Y5),50,MIN(100,MAX(0,50+'02_Market_Inputs'!Y5*15)))
A6: ='02_Market_Inputs'!A6 | B6: ='02_Market_Inputs'!B6 | C6: =IF(ISBLANK('02_Market_Inputs'!E6),50,MIN(100,MAX(0,100-('02_Market_Inputs'!E6-1)*14))) | D6: =IF(ISBLANK('02_Market_Inputs'!F6),50,MIN(100,MAX(0,50-'02_Market_Inputs'!F6*100))) | E6: =IF(ISBLANK('02_Market_Inputs'!I6),50,MIN(100,MAX(0,50-'02_Market_Inputs'!I6*15))) | F6: =IF(ISBLANK('02_Market_Inputs'!J6),50,MIN(100,MAX(0,80-ABS('02_Market_Inputs'!J6-12)*4))) | G6: =IF(OR(ISBLANK('02_Market_Inputs'!G6),ISBLANK('02_Market_Inputs'!H6)),50,(MIN(100,MAX(0,100-('02_Market_Inputs'!G6-2.5)*28.5))+MIN(100,MAX(0,('02_Market_Inputs'!H6+0.2)*58)))/2) | H6: =IF(ISBLANK('02_Market_Inputs'!K6),50,MIN(100,MAX(0,50-'02_Market_Inputs'!K6*20))) | I6: =IF(ISBLANK('02_Market_Inputs'!L6),50,MIN(100,MAX(0,100-'02_Market_Inputs'!L6*20))) | J6: =IF(ISBLANK('02_Market_Inputs'!M6),50,MIN(100,MAX(0,50+'02_Market_Inputs'!M6*15))) | K6: =IF(ISBLANK('02_Market_Inputs'!O6),50,MIN(100,MAX(0,50+'02_Market_Inputs'!O6*15))) | L6: =IF(OR(ISBLANK('02_Market_Inputs'!P6),'02_Market_Inputs'!P6<=0),50,MIN(100,MAX(0,100-'02_Market_Inputs'!P6))) | M6: =IF(ISBLANK('02_Market_Inputs'!Q6),50,MIN(100,MAX(0,50-'02_Market_Inputs'!Q6*25))) | N6: =IF(ISBLANK('02_Market_Inputs'!R6),50,MIN(100,MAX(0,50-'02_Market_Inputs'!R6*25))) | O6: =IF(ISBLANK('02_Market_Inputs'!S6),50,MIN(100,MAX(0,100-'02_Market_Inputs'!S6))) | P6: =IF(ISBLANK('02_Market_Inputs'!T6),50,MIN(100,MAX(0,50+'02_Market_Inputs'!T6*25))) | Q6: ='06_MLR_Regression'!H6 | R6: ='07_VAR_Granger'!K6 | S6: ='08_ML_Validation'!K6 | T6: ='08_ML_Validation'!L6 | U6: =IF('02_Market_Inputs'!W6="completed",85,IF('02_Market_Inputs'!W6="confirmed",75,IF('02_Market_Inputs'!W6="pending",55,50)))+IF('02_Market_Inputs'!X6<=1,20,IF('02_Market_Inputs'!X6<=2,12,IF('02_Market_Inputs'!X6<=3,6,0))) | V6: =IF(ISBLANK('02_Market_Inputs'!V6),50,MIN(100,MAX(0,50+'02_Market_Inputs'!V6*100))) | W6: =IF(ISBLANK('02_Market_Inputs'!Y6),50,MIN(100,MAX(0,50+'02_Market_Inputs'!Y6*15)))
A7: ='02_Market_Inputs'!A7 | B7: ='02_Market_Inputs'!B7 | C7: =IF(ISBLANK('02_Market_Inputs'!E7),50,MIN(100,MAX(0,100-('02_Market_Inputs'!E7-1)*14))) | D7: =IF(ISBLANK('02_Market_Inputs'!F7),50,MIN(100,MAX(0,50-'02_Market_Inputs'!F7*100))) | E7: =IF(ISBLANK('02_Market_Inputs'!I7),50,MIN(100,MAX(0,50-'02_Market_Inputs'!I7*15))) | F7: =IF(ISBLANK('02_Market_Inputs'!J7),50,MIN(100,MAX(0,80-ABS('02_Market_Inputs'!J7-12)*4))) | G7: =IF(OR(ISBLANK('02_Market_Inputs'!G7),ISBLANK('02_Market_Inputs'!H7)),50,(MIN(100,MAX(0,100-('02_Market_Inputs'!G7-2.5)*28.5))+MIN(100,MAX(0,('02_Market_Inputs'!H7+0.2)*58)))/2) | H7: =IF(ISBLANK('02_Market_Inputs'!K7),50,MIN(100,MAX(0,50-'02_Market_Inputs'!K7*20))) | I7: =IF(ISBLANK('02_Market_Inputs'!L7),50,MIN(100,MAX(0,100-'02_Market_Inputs'!L7*20))) | J7: =IF(ISBLANK('02_Market_Inputs'!M7),50,MIN(100,MAX(0,50+'02_Market_Inputs'!M7*15))) | K7: =IF(ISBLANK('02_Market_Inputs'!O7),50,MIN(100,MAX(0,50+'02_Market_Inputs'!O7*15))) | L7: =IF(OR(ISBLANK('02_Market_Inputs'!P7),'02_Market_Inputs'!P7<=0),50,MIN(100,MAX(0,100-'02_Market_Inputs'!P7))) | M7: =IF(ISBLANK('02_Market_Inputs'!Q7),50,MIN(100,MAX(0,50-'02_Market_Inputs'!Q7*25))) | N7: =IF(ISBLANK('02_Market_Inputs'!R7),50,MIN(100,MAX(0,50-'02_Market_Inputs'!R7*25))) | O7: =IF(ISBLANK('02_Market_Inputs'!S7),50,MIN(100,MAX(0,100-'02_Market_Inputs'!S7))) | P7: =IF(ISBLANK('02_Market_Inputs'!T7),50,MIN(100,MAX(0,50+'02_Market_Inputs'!T7*25))) | Q7: ='06_MLR_Regression'!H7 | R7: ='07_VAR_Granger'!K7 | S7: ='08_ML_Validation'!K7 | T7: ='08_ML_Validation'!L7 | U7: =IF('02_Market_Inputs'!W7="completed",85,IF('02_Market_Inputs'!W7="confirmed",75,IF('02_Market_Inputs'!W7="pending",55,50)))+IF('02_Market_Inputs'!X7<=1,20,IF('02_Market_Inputs'!X7<=2,12,IF('02_Market_Inputs'!X7<=3,6,0))) | V7: =IF(ISBLANK('02_Market_Inputs'!V7),50,MIN(100,MAX(0,50+'02_Market_Inputs'!V7*100))) | W7: =IF(ISBLANK('02_Market_Inputs'!Y7),50,MIN(100,MAX(0,50+'02_Market_Inputs'!Y7*15)))
A8: ='02_Market_Inputs'!A8 | B8: ='02_Market_Inputs'!B8 | C8: =IF(ISBLANK('02_Market_Inputs'!E8),50,MIN(100,MAX(0,100-('02_Market_Inputs'!E8-1)*14))) | D8: =IF(ISBLANK('02_Market_Inputs'!F8),50,MIN(100,MAX(0,50-'02_Market_Inputs'!F8*100))) | E8: =IF(ISBLANK('02_Market_Inputs'!I8),50,MIN(100,MAX(0,50-'02_Market_Inputs'!I8*15))) | F8: =IF(ISBLANK('02_Market_Inputs'!J8),50,MIN(100,MAX(0,80-ABS('02_Market_Inputs'!J8-12)*4))) | G8: =IF(OR(ISBLANK('02_Market_Inputs'!G8),ISBLANK('02_Market_Inputs'!H8)),50,(MIN(100,MAX(0,100-('02_Market_Inputs'!G8-2.5)*28.5))+MIN(100,MAX(0,('02_Market_Inputs'!H8+0.2)*58)))/2) | H8: =IF(ISBLANK('02_Market_Inputs'!K8),50,MIN(100,MAX(0,50-'02_Market_Inputs'!K8*20))) | I8: =IF(ISBLANK('02_Market_Inputs'!L8),50,MIN(100,MAX(0,100-'02_Market_Inputs'!L8*20))) | J8: =IF(ISBLANK('02_Market_Inputs'!M8),50,MIN(100,MAX(0,50+'02_Market_Inputs'!M8*15))) | K8: =IF(ISBLANK('02_Market_Inputs'!O8),50,MIN(100,MAX(0,50+'02_Market_Inputs'!O8*15))) | L8: =IF(OR(ISBLANK('02_Market_Inputs'!P8),'02_Market_Inputs'!P8<=0),50,MIN(100,MAX(0,100-'02_Market_Inputs'!P8))) | M8: =IF(ISBLANK('02_Market_Inputs'!Q8),50,MIN(100,MAX(0,50-'02_Market_Inputs'!Q8*25))) | N8: =IF(ISBLANK('02_Market_Inputs'!R8),50,MIN(100,MAX(0,50-'02_Market_Inputs'!R8*25))) | O8: =IF(ISBLANK('02_Market_Inputs'!S8),50,MIN(100,MAX(0,100-'02_Market_Inputs'!S8))) | P8: =IF(ISBLANK('02_Market_Inputs'!T8),50,MIN(100,MAX(0,50+'02_Market_Inputs'!T8*25))) | Q8: ='06_MLR_Regression'!H8 | R8: ='07_VAR_Granger'!K8 | S8: ='08_ML_Validation'!K8 | T8: ='08_ML_Validation'!L8 | U8: =IF('02_Market_Inputs'!W8="completed",85,IF('02_Market_Inputs'!W8="confirmed",75,IF('02_Market_Inputs'!W8="pending",55,50)))+IF('02_Market_Inputs'!X8<=1,20,IF('02_Market_Inputs'!X8<=2,12,IF('02_Market_Inputs'!X8<=3,6,0))) | V8: =IF(ISBLANK('02_Market_Inputs'!V8),50,MIN(100,MAX(0,50+'02_Market_Inputs'!V8*100))) | W8: =IF(ISBLANK('02_Market_Inputs'!Y8),50,MIN(100,MAX(0,50+'02_Market_Inputs'!Y8*15)))
A9: ='02_Market_Inputs'!A9 | B9: ='02_Market_Inputs'!B9 | C9: =IF(ISBLANK('02_Market_Inputs'!E9),50,MIN(100,MAX(0,100-('02_Market_Inputs'!E9-1)*14))) | D9: =IF(ISBLANK('02_Market_Inputs'!F9),50,MIN(100,MAX(0,50-'02_Market_Inputs'!F9*100))) | E9: =IF(ISBLANK('02_Market_Inputs'!I9),50,MIN(100,MAX(0,50-'02_Market_Inputs'!I9*15))) | F9: =IF(ISBLANK('02_Market_Inputs'!J9),50,MIN(100,MAX(0,80-ABS('02_Market_Inputs'!J9-12)*4))) | G9: =IF(OR(ISBLANK('02_Market_Inputs'!G9),ISBLANK('02_Market_Inputs'!H9)),50,(MIN(100,MAX(0,100-('02_Market_Inputs'!G9-2.5)*28.5))+MIN(100,MAX(0,('02_Market_Inputs'!H9+0.2)*58)))/2) | H9: =IF(ISBLANK('02_Market_Inputs'!K9),50,MIN(100,MAX(0,50-'02_Market_Inputs'!K9*20))) | I9: =IF(ISBLANK('02_Market_Inputs'!L9),50,MIN(100,MAX(0,100-'02_Market_Inputs'!L9*20))) | J9: =IF(ISBLANK('02_Market_Inputs'!M9),50,MIN(100,MAX(0,50+'02_Market_Inputs'!M9*15))) | K9: =IF(ISBLANK('02_Market_Inputs'!O9),50,MIN(100,MAX(0,50+'02_Market_Inputs'!O9*15))) | L9: =IF(OR(ISBLANK('02_Market_Inputs'!P9),'02_Market_Inputs'!P9<=0),50,MIN(100,MAX(0,100-'02_Market_Inputs'!P9))) | M9: =IF(ISBLANK('02_Market_Inputs'!Q9),50,MIN(100,MAX(0,50-'02_Market_Inputs'!Q9*25))) | N9: =IF(ISBLANK('02_Market_Inputs'!R9),50,MIN(100,MAX(0,50-'02_Market_Inputs'!R9*25))) | O9: =IF(ISBLANK('02_Market_Inputs'!S9),50,MIN(100,MAX(0,100-'02_Market_Inputs'!S9))) | P9: =IF(ISBLANK('02_Market_Inputs'!T9),50,MIN(100,MAX(0,50+'02_Market_Inputs'!T9*25))) | Q9: ='06_MLR_Regression'!H9 | R9: ='07_VAR_Granger'!K9 | S9: ='08_ML_Validation'!K9 | T9: ='08_ML_Validation'!L9 | U9: =IF('02_Market_Inputs'!W9="completed",85,IF('02_Market_Inputs'!W9="confirmed",75,IF('02_Market_Inputs'!W9="pending",55,50)))+IF('02_Market_Inputs'!X9<=1,20,IF('02_Market_Inputs'!X9<=2,12,IF('02_Market_Inputs'!X9<=3,6,0))) | V9: =IF(ISBLANK('02_Market_Inputs'!V9),50,MIN(100,MAX(0,50+'02_Market_Inputs'!V9*100))) | W9: =IF(ISBLANK('02_Market_Inputs'!Y9),50,MIN(100,MAX(0,50+'02_Market_Inputs'!Y9*15)))
A10: ='02_Market_Inputs'!A10 | B10: ='02_Market_Inputs'!B10 | C10: =IF(ISBLANK('02_Market_Inputs'!E10),50,MIN(100,MAX(0,100-('02_Market_Inputs'!E10-1)*14))) | D10: =IF(ISBLANK('02_Market_Inputs'!F10),50,MIN(100,MAX(0,50-'02_Market_Inputs'!F10*100))) | E10: =IF(ISBLANK('02_Market_Inputs'!I10),50,MIN(100,MAX(0,50-'02_Market_Inputs'!I10*15))) | F10: =IF(ISBLANK('02_Market_Inputs'!J10),50,MIN(100,MAX(0,80-ABS('02_Market_Inputs'!J10-12)*4))) | G10: =IF(OR(ISBLANK('02_Market_Inputs'!G10),ISBLANK('02_Market_Inputs'!H10)),50,(MIN(100,MAX(0,100-('02_Market_Inputs'!G10-2.5)*28.5))+MIN(100,MAX(0,('02_Market_Inputs'!H10+0.2)*58)))/2) | H10: =IF(ISBLANK('02_Market_Inputs'!K10),50,MIN(100,MAX(0,50-'02_Market_Inputs'!K10*20))) | I10: =IF(ISBLANK('02_Market_Inputs'!L10),50,MIN(100,MAX(0,100-'02_Market_Inputs'!L10*20))) | J10: =IF(ISBLANK('02_Market_Inputs'!M10),50,MIN(100,MAX(0,50+'02_Market_Inputs'!M10*15))) | K10: =IF(ISBLANK('02_Market_Inputs'!O10),50,MIN(100,MAX(0,50+'02_Market_Inputs'!O10*15))) | L10: =IF(OR(ISBLANK('02_Market_Inputs'!P10),'02_Market_Inputs'!P10<=0),50,MIN(100,MAX(0,100-'02_Market_Inputs'!P10))) | M10: =IF(ISBLANK('02_Market_Inputs'!Q10),50,MIN(100,MAX(0,50-'02_Market_Inputs'!Q10*25))) | N10: =IF(ISBLANK('02_Market_Inputs'!R10),50,MIN(100,MAX(0,50-'02_Market_Inputs'!R10*25))) | O10: =IF(ISBLANK('02_Market_Inputs'!S10),50,MIN(100,MAX(0,100-'02_Market_Inputs'!S10))) | P10: =IF(ISBLANK('02_Market_Inputs'!T10),50,MIN(100,MAX(0,50+'02_Market_Inputs'!T10*25))) | Q10: ='06_MLR_Regression'!H10 | R10: ='07_VAR_Granger'!K10 | S10: ='08_ML_Validation'!K10 | T10: ='08_ML_Validation'!L10 | U10: =IF('02_Market_Inputs'!W10="completed",85,IF('02_Market_Inputs'!W10="confirmed",75,IF('02_Market_Inputs'!W10="pending",55,50)))+IF('02_Market_Inputs'!X10<=1,20,IF('02_Market_Inputs'!X10<=2,12,IF('02_Market_Inputs'!X10<=3,6,0))) | V10: =IF(ISBLANK('02_Market_Inputs'!V10),50,MIN(100,MAX(0,50+'02_Market_Inputs'!V10*100))) | W10: =IF(ISBLANK('02_Market_Inputs'!Y10),50,MIN(100,MAX(0,50+'02_Market_Inputs'!Y10*15)))
A11: ='02_Market_Inputs'!A11 | B11: ='02_Market_Inputs'!B11 | C11: =IF(ISBLANK('02_Market_Inputs'!E11),50,MIN(100,MAX(0,100-('02_Market_Inputs'!E11-1)*14))) | D11: =IF(ISBLANK('02_Market_Inputs'!F11),50,MIN(100,MAX(0,50-'02_Market_Inputs'!F11*100))) | E11: =IF(ISBLANK('02_Market_Inputs'!I11),50,MIN(100,MAX(0,50-'02_Market_Inputs'!I11*15))) | F11: =IF(ISBLANK('02_Market_Inputs'!J11),50,MIN(100,MAX(0,80-ABS('02_Market_Inputs'!J11-12)*4))) | G11: =IF(OR(ISBLANK('02_Market_Inputs'!G11),ISBLANK('02_Market_Inputs'!H11)),50,(MIN(100,MAX(0,100-('02_Market_Inputs'!G11-2.5)*28.5))+MIN(100,MAX(0,('02_Market_Inputs'!H11+0.2)*58)))/2) | H11: =IF(ISBLANK('02_Market_Inputs'!K11),50,MIN(100,MAX(0,50-'02_Market_Inputs'!K11*20))) | I11: =IF(ISBLANK('02_Market_Inputs'!L11),50,MIN(100,MAX(0,100-'02_Market_Inputs'!L11*20))) | J11: =IF(ISBLANK('02_Market_Inputs'!M11),50,MIN(100,MAX(0,50+'02_Market_Inputs'!M11*15))) | K11: =IF(ISBLANK('02_Market_Inputs'!O11),50,MIN(100,MAX(0,50+'02_Market_Inputs'!O11*15))) | L11: =IF(OR(ISBLANK('02_Market_Inputs'!P11),'02_Market_Inputs'!P11<=0),50,MIN(100,MAX(0,100-'02_Market_Inputs'!P11))) | M11: =IF(ISBLANK('02_Market_Inputs'!Q11),50,MIN(100,MAX(0,50-'02_Market_Inputs'!Q11*25))) | N11: =IF(ISBLANK('02_Market_Inputs'!R11),50,MIN(100,MAX(0,50-'02_Market_Inputs'!R11*25))) | O11: =IF(ISBLANK('02_Market_Inputs'!S11),50,MIN(100,MAX(0,100-'02_Market_Inputs'!S11))) | P11: =IF(ISBLANK('02_Market_Inputs'!T11),50,MIN(100,MAX(0,50+'02_Market_Inputs'!T11*25))) | Q11: ='06_MLR_Regression'!H11 | R11: ='07_VAR_Granger'!K11 | S11: ='08_ML_Validation'!K11 | T11: ='08_ML_Validation'!L11 | U11: =IF('02_Market_Inputs'!W11="completed",85,IF('02_Market_Inputs'!W11="confirmed",75,IF('02_Market_Inputs'!W11="pending",55,50)))+IF('02_Market_Inputs'!X11<=1,20,IF('02_Market_Inputs'!X11<=2,12,IF('02_Market_Inputs'!X11<=3,6,0))) | V11: =IF(ISBLANK('02_Market_Inputs'!V11),50,MIN(100,MAX(0,50+'02_Market_Inputs'!V11*100))) | W11: =IF(ISBLANK('02_Market_Inputs'!Y11),50,MIN(100,MAX(0,50+'02_Market_Inputs'!Y11*15)))
A12: ='02_Market_Inputs'!A12 | B12: ='02_Market_Inputs'!B12 | C12: =IF(ISBLANK('02_Market_Inputs'!E12),50,MIN(100,MAX(0,100-('02_Market_Inputs'!E12-1)*14))) | D12: =IF(ISBLANK('02_Market_Inputs'!F12),50,MIN(100,MAX(0,50-'02_Market_Inputs'!F12*100))) | E12: =IF(ISBLANK('02_Market_Inputs'!I12),50,MIN(100,MAX(0,50-'02_Market_Inputs'!I12*15))) | F12: =IF(ISBLANK('02_Market_Inputs'!J12),50,MIN(100,MAX(0,80-ABS('02_Market_Inputs'!J12-12)*4))) | G12: =IF(OR(ISBLANK('02_Market_Inputs'!G12),ISBLANK('02_Market_Inputs'!H12)),50,(MIN(100,MAX(0,100-('02_Market_Inputs'!G12-2.5)*28.5))+MIN(100,MAX(0,('02_Market_Inputs'!H12+0.2)*58)))/2) | H12: =IF(ISBLANK('02_Market_Inputs'!K12),50,MIN(100,MAX(0,50-'02_Market_Inputs'!K12*20))) | I12: =IF(ISBLANK('02_Market_Inputs'!L12),50,MIN(100,MAX(0,100-'02_Market_Inputs'!L12*20))) | J12: =IF(ISBLANK('02_Market_Inputs'!M12),50,MIN(100,MAX(0,50+'02_Market_Inputs'!M12*15))) | K12: =IF(ISBLANK('02_Market_Inputs'!O12),50,MIN(100,MAX(0,50+'02_Market_Inputs'!O12*15))) | L12: =IF(OR(ISBLANK('02_Market_Inputs'!P12),'02_Market_Inputs'!P12<=0),50,MIN(100,MAX(0,100-'02_Market_Inputs'!P12))) | M12: =IF(ISBLANK('02_Market_Inputs'!Q12),50,MIN(100,MAX(0,50-'02_Market_Inputs'!Q12*25))) | N12: =IF(ISBLANK('02_Market_Inputs'!R12),50,MIN(100,MAX(0,50-'02_Market_Inputs'!R12*25))) | O12: =IF(ISBLANK('02_Market_Inputs'!S12),50,MIN(100,MAX(0,100-'02_Market_Inputs'!S12))) | P12: =IF(ISBLANK('02_Market_Inputs'!T12),50,MIN(100,MAX(0,50+'02_Market_Inputs'!T12*25))) | Q12: ='06_MLR_Regression'!H12 | R12: ='07_VAR_Granger'!K12 | S12: ='08_ML_Validation'!K12 | T12: ='08_ML_Validation'!L12 | U12: =IF('02_Market_Inputs'!W12="completed",85,IF('02_Market_Inputs'!W12="confirmed",75,IF('02_Market_Inputs'!W12="pending",55,50)))+IF('02_Market_Inputs'!X12<=1,20,IF('02_Market_Inputs'!X12<=2,12,IF('02_Market_Inputs'!X12<=3,6,0))) | V12: =IF(ISBLANK('02_Market_Inputs'!V12),50,MIN(100,MAX(0,50+'02_Market_Inputs'!V12*100))) | W12: =IF(ISBLANK('02_Market_Inputs'!Y12),50,MIN(100,MAX(0,50+'02_Market_Inputs'!Y12*15)))
A13: ='02_Market_Inputs'!A13 | B13: ='02_Market_Inputs'!B13 | C13: =IF(ISBLANK('02_Market_Inputs'!E13),50,MIN(100,MAX(0,100-('02_Market_Inputs'!E13-1)*14))) | D13: =IF(ISBLANK('02_Market_Inputs'!F13),50,MIN(100,MAX(0,50-'02_Market_Inputs'!F13*100))) | E13: =IF(ISBLANK('02_Market_Inputs'!I13),50,MIN(100,MAX(0,50-'02_Market_Inputs'!I13*15))) | F13: =IF(ISBLANK('02_Market_Inputs'!J13),50,MIN(100,MAX(0,80-ABS('02_Market_Inputs'!J13-12)*4))) | G13: =IF(OR(ISBLANK('02_Market_Inputs'!G13),ISBLANK('02_Market_Inputs'!H13)),50,(MIN(100,MAX(0,100-('02_Market_Inputs'!G13-2.5)*28.5))+MIN(100,MAX(0,('02_Market_Inputs'!H13+0.2)*58)))/2) | H13: =IF(ISBLANK('02_Market_Inputs'!K13),50,MIN(100,MAX(0,50-'02_Market_Inputs'!K13*20))) | I13: =IF(ISBLANK('02_Market_Inputs'!L13),50,MIN(100,MAX(0,100-'02_Market_Inputs'!L13*20))) | J13: =IF(ISBLANK('02_Market_Inputs'!M13),50,MIN(100,MAX(0,50+'02_Market_Inputs'!M13*15))) | K13: =IF(ISBLANK('02_Market_Inputs'!O13),50,MIN(100,MAX(0,50+'02_Market_Inputs'!O13*15))) | L13: =IF(OR(ISBLANK('02_Market_Inputs'!P13),'02_Market_Inputs'!P13<=0),50,MIN(100,MAX(0,100-'02_Market_Inputs'!P13))) | M13: =IF(ISBLANK('02_Market_Inputs'!Q13),50,MIN(100,MAX(0,50-'02_Market_Inputs'!Q13*25))) | N13: =IF(ISBLANK('02_Market_Inputs'!R13),50,MIN(100,MAX(0,50-'02_Market_Inputs'!R13*25))) | O13: =IF(ISBLANK('02_Market_Inputs'!S13),50,MIN(100,MAX(0,100-'02_Market_Inputs'!S13))) | P13: =IF(ISBLANK('02_Market_Inputs'!T13),50,MIN(100,MAX(0,50+'02_Market_Inputs'!T13*25))) | Q13: ='06_MLR_Regression'!H13 | R13: ='07_VAR_Granger'!K13 | S13: ='08_ML_Validation'!K13 | T13: ='08_ML_Validation'!L13 | U13: =IF('02_Market_Inputs'!W13="completed",85,IF('02_Market_Inputs'!W13="confirmed",75,IF('02_Market_Inputs'!W13="pending",55,50)))+IF('02_Market_Inputs'!X13<=1,20,IF('02_Market_Inputs'!X13<=2,12,IF('02_Market_Inputs'!X13<=3,6,0))) | V13: =IF(ISBLANK('02_Market_Inputs'!V13),50,MIN(100,MAX(0,50+'02_Market_Inputs'!V13*100))) | W13: =IF(ISBLANK('02_Market_Inputs'!Y13),50,MIN(100,MAX(0,50+'02_Market_Inputs'!Y13*15)))
A14: ='02_Market_Inputs'!A14 | B14: ='02_Market_Inputs'!B14 | C14: =IF(ISBLANK('02_Market_Inputs'!E14),50,MIN(100,MAX(0,100-('02_Market_Inputs'!E14-1)*14))) | D14: =IF(ISBLANK('02_Market_Inputs'!F14),50,MIN(100,MAX(0,50-'02_Market_Inputs'!F14*100))) | E14: =IF(ISBLANK('02_Market_Inputs'!I14),50,MIN(100,MAX(0,50-'02_Market_Inputs'!I14*15))) | F14: =IF(ISBLANK('02_Market_Inputs'!J14),50,MIN(100,MAX(0,80-ABS('02_Market_Inputs'!J14-12)*4))) | G14: =IF(OR(ISBLANK('02_Market_Inputs'!G14),ISBLANK('02_Market_Inputs'!H14)),50,(MIN(100,MAX(0,100-('02_Market_Inputs'!G14-2.5)*28.5))+MIN(100,MAX(0,('02_Market_Inputs'!H14+0.2)*58)))/2) | H14: =IF(ISBLANK('02_Market_Inputs'!K14),50,MIN(100,MAX(0,50-'02_Market_Inputs'!K14*20))) | I14: =IF(ISBLANK('02_Market_Inputs'!L14),50,MIN(100,MAX(0,100-'02_Market_Inputs'!L14*20))) | J14: =IF(ISBLANK('02_Market_Inputs'!M14),50,MIN(100,MAX(0,50+'02_Market_Inputs'!M14*15))) | K14: =IF(ISBLANK('02_Market_Inputs'!O14),50,MIN(100,MAX(0,50+'02_Market_Inputs'!O14*15))) | L14: =IF(OR(ISBLANK('02_Market_Inputs'!P14),'02_Market_Inputs'!P14<=0),50,MIN(100,MAX(0,100-'02_Market_Inputs'!P14))) | M14: =IF(ISBLANK('02_Market_Inputs'!Q14),50,MIN(100,MAX(0,50-'02_Market_Inputs'!Q14*25))) | N14: =IF(ISBLANK('02_Market_Inputs'!R14),50,MIN(100,MAX(0,50-'02_Market_Inputs'!R14*25))) | O14: =IF(ISBLANK('02_Market_Inputs'!S14),50,MIN(100,MAX(0,100-'02_Market_Inputs'!S14))) | P14: =IF(ISBLANK('02_Market_Inputs'!T14),50,MIN(100,MAX(0,50+'02_Market_Inputs'!T14*25))) | Q14: ='06_MLR_Regression'!H14 | R14: ='07_VAR_Granger'!K14 | S14: ='08_ML_Validation'!K14 | T14: ='08_ML_Validation'!L14 | U14: =IF('02_Market_Inputs'!W14="completed",85,IF('02_Market_Inputs'!W14="confirmed",75,IF('02_Market_Inputs'!W14="pending",55,50)))+IF('02_Market_Inputs'!X14<=1,20,IF('02_Market_Inputs'!X14<=2,12,IF('02_Market_Inputs'!X14<=3,6,0))) | V14: =IF(ISBLANK('02_Market_Inputs'!V14),50,MIN(100,MAX(0,50+'02_Market_Inputs'!V14*100))) | W14: =IF(ISBLANK('02_Market_Inputs'!Y14),50,MIN(100,MAX(0,50+'02_Market_Inputs'!Y14*15)))
A15: ='02_Market_Inputs'!A15 | B15: ='02_Market_Inputs'!B15 | C15: =IF(ISBLANK('02_Market_Inputs'!E15),50,MIN(100,MAX(0,100-('02_Market_Inputs'!E15-1)*14))) | D15: =IF(ISBLANK('02_Market_Inputs'!F15),50,MIN(100,MAX(0,50-'02_Market_Inputs'!F15*100))) | E15: =IF(ISBLANK('02_Market_Inputs'!I15),50,MIN(100,MAX(0,50-'02_Market_Inputs'!I15*15))) | F15: =IF(ISBLANK('02_Market_Inputs'!J15),50,MIN(100,MAX(0,80-ABS('02_Market_Inputs'!J15-12)*4))) | G15: =IF(OR(ISBLANK('02_Market_Inputs'!G15),ISBLANK('02_Market_Inputs'!H15)),50,(MIN(100,MAX(0,100-('02_Market_Inputs'!G15-2.5)*28.5))+MIN(100,MAX(0,('02_Market_Inputs'!H15+0.2)*58)))/2) | H15: =IF(ISBLANK('02_Market_Inputs'!K15),50,MIN(100,MAX(0,50-'02_Market_Inputs'!K15*20))) | I15: =IF(ISBLANK('02_Market_Inputs'!L15),50,MIN(100,MAX(0,100-'02_Market_Inputs'!L15*20))) | J15: =IF(ISBLANK('02_Market_Inputs'!M15),50,MIN(100,MAX(0,50+'02_Market_Inputs'!M15*15))) | K15: =IF(ISBLANK('02_Market_Inputs'!O15),50,MIN(100,MAX(0,50+'02_Market_Inputs'!O15*15))) | L15: =IF(OR(ISBLANK('02_Market_Inputs'!P15),'02_Market_Inputs'!P15<=0),50,MIN(100,MAX(0,100-'02_Market_Inputs'!P15))) | M15: =IF(ISBLANK('02_Market_Inputs'!Q15),50,MIN(100,MAX(0,50-'02_Market_Inputs'!Q15*25))) | N15: =IF(ISBLANK('02_Market_Inputs'!R15),50,MIN(100,MAX(0,50-'02_Market_Inputs'!R15*25))) | O15: =IF(ISBLANK('02_Market_Inputs'!S15),50,MIN(100,MAX(0,100-'02_Market_Inputs'!S15))) | P15: =IF(ISBLANK('02_Market_Inputs'!T15),50,MIN(100,MAX(0,50+'02_Market_Inputs'!T15*25))) | Q15: ='06_MLR_Regression'!H15 | R15: ='07_VAR_Granger'!K15 | S15: ='08_ML_Validation'!K15 | T15: ='08_ML_Validation'!L15 | U15: =IF('02_Market_Inputs'!W15="completed",85,IF('02_Market_Inputs'!W15="confirmed",75,IF('02_Market_Inputs'!W15="pending",55,50)))+IF('02_Market_Inputs'!X15<=1,20,IF('02_Market_Inputs'!X15<=2,12,IF('02_Market_Inputs'!X15<=3,6,0))) | V15: =IF(ISBLANK('02_Market_Inputs'!V15),50,MIN(100,MAX(0,50+'02_Market_Inputs'!V15*100))) | W15: =IF(ISBLANK('02_Market_Inputs'!Y15),50,MIN(100,MAX(0,50+'02_Market_Inputs'!Y15*15)))
A16: ='02_Market_Inputs'!A16 | B16: ='02_Market_Inputs'!B16 | C16: =IF(ISBLANK('02_Market_Inputs'!E16),50,MIN(100,MAX(0,100-('02_Market_Inputs'!E16-1)*14))) | D16: =IF(ISBLANK('02_Market_Inputs'!F16),50,MIN(100,MAX(0,50-'02_Market_Inputs'!F16*100))) | E16: =IF(ISBLANK('02_Market_Inputs'!I16),50,MIN(100,MAX(0,50-'02_Market_Inputs'!I16*15))) | F16: =IF(ISBLANK('02_Market_Inputs'!J16),50,MIN(100,MAX(0,80-ABS('02_Market_Inputs'!J16-12)*4))) | G16: =IF(OR(ISBLANK('02_Market_Inputs'!G16),ISBLANK('02_Market_Inputs'!H16)),50,(MIN(100,MAX(0,100-('02_Market_Inputs'!G16-2.5)*28.5))+MIN(100,MAX(0,('02_Market_Inputs'!H16+0.2)*58)))/2) | H16: =IF(ISBLANK('02_Market_Inputs'!K16),50,MIN(100,MAX(0,50-'02_Market_Inputs'!K16*20))) | I16: =IF(ISBLANK('02_Market_Inputs'!L16),50,MIN(100,MAX(0,100-'02_Market_Inputs'!L16*20))) | J16: =IF(ISBLANK('02_Market_Inputs'!M16),50,MIN(100,MAX(0,50+'02_Market_Inputs'!M16*15))) | K16: =IF(ISBLANK('02_Market_Inputs'!O16),50,MIN(100,MAX(0,50+'02_Market_Inputs'!O16*15))) | L16: =IF(OR(ISBLANK('02_Market_Inputs'!P16),'02_Market_Inputs'!P16<=0),50,MIN(100,MAX(0,100-'02_Market_Inputs'!P16))) | M16: =IF(ISBLANK('02_Market_Inputs'!Q16),50,MIN(100,MAX(0,50-'02_Market_Inputs'!Q16*25))) | N16: =IF(ISBLANK('02_Market_Inputs'!R16),50,MIN(100,MAX(0,50-'02_Market_Inputs'!R16*25))) | O16: =IF(ISBLANK('02_Market_Inputs'!S16),50,MIN(100,MAX(0,100-'02_Market_Inputs'!S16))) | P16: =IF(ISBLANK('02_Market_Inputs'!T16),50,MIN(100,MAX(0,50+'02_Market_Inputs'!T16*25))) | Q16: ='06_MLR_Regression'!H16 | R16: ='07_VAR_Granger'!K16 | S16: ='08_ML_Validation'!K16 | T16: ='08_ML_Validation'!L16 | U16: =IF('02_Market_Inputs'!W16="completed",85,IF('02_Market_Inputs'!W16="confirmed",75,IF('02_Market_Inputs'!W16="pending",55,50)))+IF('02_Market_Inputs'!X16<=1,20,IF('02_Market_Inputs'!X16<=2,12,IF('02_Market_Inputs'!X16<=3,6,0))) | V16: =IF(ISBLANK('02_Market_Inputs'!V16),50,MIN(100,MAX(0,50+'02_Market_Inputs'!V16*100))) | W16: =IF(ISBLANK('02_Market_Inputs'!Y16),50,MIN(100,MAX(0,50+'02_Market_Inputs'!Y16*15)))
... A28: ='02_Market_Inputs'!A28 | B28: ='02_Market_Inputs'!B28 | C28: =IF(ISBLANK('02_Market_Inputs'!E28),50,MIN(100,MAX(0,100-('02_Market_Inputs'!E28-1)*14))) | D28: =IF(ISBLANK('02_Market_Inputs'!F28),50,MIN(100,MAX(0,50-'02_Market_Inputs'!F28*100))) | E28: =IF(ISBLANK('02_Market_Inputs'!I28),50,MIN(100,MAX(0,50-'02_Market_Inputs'!I28*15))) | F28: =IF(ISBLANK('02_Market_Inputs'!J28),50,MIN(100,MAX(0,80-ABS('02_Market_Inputs'!J28-12)*4))) | G28: =IF(OR(ISBLANK('02_Market_Inputs'!G28),ISBLANK('02_Market_Inputs'!H28)),50,(MIN(100,MAX(0,100-('02_Market_Inputs'!G28-2.5)*28.5))+MIN(100,MAX(0,('02_Market_Inputs'!H28+0.2)*58)))/2) | H28: =IF(ISBLANK('02_Market_Inputs'!K28),50,MIN(100,MAX(0,50-'02_Market_Inputs'!K28*20))) | I28: =IF(ISBLANK('02_Market_Inputs'!L28),50,MIN(100,MAX(0,100-'02_Market_Inputs'!L28*20))) | J28: =IF(ISBLANK('02_Market_Inputs'!M28),50,MIN(100,MAX(0,50+'02_Market_Inputs'!M28*15))) | K28: =IF(ISBLANK('02_Market_Inputs'!O28),50,MIN(100,MAX(0,50+'02_Market_Inputs'!O28*15))) | L28: =IF(OR(ISBLANK('02_Market_Inputs'!P28),'02_Market_Inputs'!P28<=0),50,MIN(100,MAX(0,100-'02_Market_Inputs'!P28))) | M28: =IF(ISBLANK('02_Market_Inputs'!Q28),50,MIN(100,MAX(0,50-'02_Market_Inputs'!Q28*25))) | N28: =IF(ISBLANK('02_Market_Inputs'!R28),50,MIN(100,MAX(0,50-'02_Market_Inputs'!R28*25))) | O28: =IF(ISBLANK('02_Market_Inputs'!S28),50,MIN(100,MAX(0,100-'02_Market_Inputs'!S28))) | P28: =IF(ISBLANK('02_Market_Inputs'!T28),50,MIN(100,MAX(0,50+'02_Market_Inputs'!T28*25))) | Q28: ='06_MLR_Regression'!H28 | R28: ='07_VAR_Granger'!K28 | S28: ='08_ML_Validation'!K28 | T28: ='08_ML_Validation'!L28 | U28: =IF('02_Market_Inputs'!W28="completed",85,IF('02_Market_Inputs'!W28="confirmed",75,IF('02_Market_Inputs'!W28="pending",55,50)))+IF('02_Market_Inputs'!X28<=1,20,IF('02_Market_Inputs'!X28<=2,12,IF('02_Market_Inputs'!X28<=3,6,0))) | V28: =IF(ISBLANK('02_Market_Inputs'!V28),50,MIN(100,MAX(0,50+'02_Market_Inputs'!V28*100))) | W28: =IF(ISBLANK('02_Market_Inputs'!Y28),50,MIN(100,MAX(0,50+'02_Market_Inputs'!Y28*15)))

Sheet 04_Pillar_Calculation
A1: SIX-PILLAR FORMULA CALCULATION
A2: Raw scores are rounded exactly as the production scorer, weighted contributions are rounded before summation
A4: Quarter | B4: As-of Date | C4: Macro Raw | D4: Global Raw | E4: Valuation Raw | F4: Quant Raw | G4: ML Raw | H4: Market Structure Raw | I4: Macro Weighted | J4: Global Weighted | K4: Valuation Weighted | L4: Quant Weighted | M4: ML Weighted | N4: Market Weighted | O4: Raw Composite | P4: Macro Unrounded | Q4: Global Unrounded | R4: Valuation Unrounded | S4: Quant Unrounded | T4: ML Unrounded | U4: Market Unrounded
A5: ='03_Factor_SubScores'!A5 | B5: ='03_Factor_SubScores'!B5 | C5: =ROUND(P5,2) | D5: =ROUND(Q5,2) | E5: =ROUND(R5,2) | F5: =ROUND(S5,2) | G5: =ROUND(T5,2) | H5: =ROUND(U5,2) | I5: =ROUND(P5*'01_Model_Config'!$C$6,2) | J5: =ROUND(Q5*'01_Model_Config'!$C$7,2) | K5: =ROUND(R5*'01_Model_Config'!$C$8,2) | L5: =ROUND(S5*'01_Model_Config'!$C$9,2) | M5: =ROUND(T5*'01_Model_Config'!$C$10,2) | N5: =ROUND(U5*'01_Model_Config'!$C$11,2) | O5: =SUM(I5:N5) | P5: =AVERAGE('03_Factor_SubScores'!C5:G5) | Q5: =IF('02_Market_Inputs'!O5<-2,MIN(20,IF('02_Market_Inputs'!P5>0,AVERAGE('03_Factor_SubScores'!H5:L5),AVERAGE('03_Factor_SubScores'!H5:K5))),IF('02_Market_Inputs'!P5>0,AVERAGE('03_Factor_SubScores'!H5:L5),AVERAGE('03_Factor_SubScores'!H5:K5))) | R5: =IF(ISBLANK('02_Market_Inputs'!U5),AVERAGE('03_Factor_SubScores'!M5:P5),AVERAGE('03_Factor_SubScores'!M5:P5)*0.7+'02_Market_Inputs'!U5*0.3) | S5: =MIN(100,MAX(0,AVERAGE('03_Factor_SubScores'!Q5:R5)+MIN(10,'06_MLR_Regression'!G5)+MIN(15,'07_VAR_Granger'!I5*3))) | T5: =MIN(100,MAX(0,'03_Factor_SubScores'!S5*0.3+'03_Factor_SubScores'!T5*0.7)) | U5: =MIN(100,MAX(0,AVERAGE('03_Factor_SubScores'!U5:W5)))
A6: ='03_Factor_SubScores'!A6 | B6: ='03_Factor_SubScores'!B6 | C6: =ROUND(P6,2) | D6: =ROUND(Q6,2) | E6: =ROUND(R6,2) | F6: =ROUND(S6,2) | G6: =ROUND(T6,2) | H6: =ROUND(U6,2) | I6: =ROUND(P6*'01_Model_Config'!$C$6,2) | J6: =ROUND(Q6*'01_Model_Config'!$C$7,2) | K6: =ROUND(R6*'01_Model_Config'!$C$8,2) | L6: =ROUND(S6*'01_Model_Config'!$C$9,2) | M6: =ROUND(T6*'01_Model_Config'!$C$10,2) | N6: =ROUND(U6*'01_Model_Config'!$C$11,2) | O6: =SUM(I6:N6) | P6: =AVERAGE('03_Factor_SubScores'!C6:G6) | Q6: =IF('02_Market_Inputs'!O6<-2,MIN(20,IF('02_Market_Inputs'!P6>0,AVERAGE('03_Factor_SubScores'!H6:L6),AVERAGE('03_Factor_SubScores'!H6:K6))),IF('02_Market_Inputs'!P6>0,AVERAGE('03_Factor_SubScores'!H6:L6),AVERAGE('03_Factor_SubScores'!H6:K6))) | R6: =IF(ISBLANK('02_Market_Inputs'!U6),AVERAGE('03_Factor_SubScores'!M6:P6),AVERAGE('03_Factor_SubScores'!M6:P6)*0.7+'02_Market_Inputs'!U6*0.3) | S6: =MIN(100,MAX(0,AVERAGE('03_Factor_SubScores'!Q6:R6)+MIN(10,'06_MLR_Regression'!G6)+MIN(15,'07_VAR_Granger'!I6*3))) | T6: =MIN(100,MAX(0,'03_Factor_SubScores'!S6*0.3+'03_Factor_SubScores'!T6*0.7)) | U6: =MIN(100,MAX(0,AVERAGE('03_Factor_SubScores'!U6:W6)))
A7: ='03_Factor_SubScores'!A7 | B7: ='03_Factor_SubScores'!B7 | C7: =ROUND(P7,2) | D7: =ROUND(Q7,2) | E7: =ROUND(R7,2) | F7: =ROUND(S7,2) | G7: =ROUND(T7,2) | H7: =ROUND(U7,2) | I7: =ROUND(P7*'01_Model_Config'!$C$6,2) | J7: =ROUND(Q7*'01_Model_Config'!$C$7,2) | K7: =ROUND(R7*'01_Model_Config'!$C$8,2) | L7: =ROUND(S7*'01_Model_Config'!$C$9,2) | M7: =ROUND(T7*'01_Model_Config'!$C$10,2) | N7: =ROUND(U7*'01_Model_Config'!$C$11,2) | O7: =SUM(I7:N7) | P7: =AVERAGE('03_Factor_SubScores'!C7:G7) | Q7: =IF('02_Market_Inputs'!O7<-2,MIN(20,IF('02_Market_Inputs'!P7>0,AVERAGE('03_Factor_SubScores'!H7:L7),AVERAGE('03_Factor_SubScores'!H7:K7))),IF('02_Market_Inputs'!P7>0,AVERAGE('03_Factor_SubScores'!H7:L7),AVERAGE('03_Factor_SubScores'!H7:K7))) | R7: =IF(ISBLANK('02_Market_Inputs'!U7),AVERAGE('03_Factor_SubScores'!M7:P7),AVERAGE('03_Factor_SubScores'!M7:P7)*0.7+'02_Market_Inputs'!U7*0.3) | S7: =MIN(100,MAX(0,AVERAGE('03_Factor_SubScores'!Q7:R7)+MIN(10,'06_MLR_Regression'!G7)+MIN(15,'07_VAR_Granger'!I7*3))) | T7: =MIN(100,MAX(0,'03_Factor_SubScores'!S7*0.3+'03_Factor_SubScores'!T7*0.7)) | U7: =MIN(100,MAX(0,AVERAGE('03_Factor_SubScores'!U7:W7)))
A8: ='03_Factor_SubScores'!A8 | B8: ='03_Factor_SubScores'!B8 | C8: =ROUND(P8,2) | D8: =ROUND(Q8,2) | E8: =ROUND(R8,2) | F8: =ROUND(S8,2) | G8: =ROUND(T8,2) | H8: =ROUND(U8,2) | I8: =ROUND(P8*'01_Model_Config'!$C$6,2) | J8: =ROUND(Q8*'01_Model_Config'!$C$7,2) | K8: =ROUND(R8*'01_Model_Config'!$C$8,2) | L8: =ROUND(S8*'01_Model_Config'!$C$9,2) | M8: =ROUND(T8*'01_Model_Config'!$C$10,2) | N8: =ROUND(U8*'01_Model_Config'!$C$11,2) | O8: =SUM(I8:N8) | P8: =AVERAGE('03_Factor_SubScores'!C8:G8) | Q8: =IF('02_Market_Inputs'!O8<-2,MIN(20,IF('02_Market_Inputs'!P8>0,AVERAGE('03_Factor_SubScores'!H8:L8),AVERAGE('03_Factor_SubScores'!H8:K8))),IF('02_Market_Inputs'!P8>0,AVERAGE('03_Factor_SubScores'!H8:L8),AVERAGE('03_Factor_SubScores'!H8:K8))) | R8: =IF(ISBLANK('02_Market_Inputs'!U8),AVERAGE('03_Factor_SubScores'!M8:P8),AVERAGE('03_Factor_SubScores'!M8:P8)*0.7+'02_Market_Inputs'!U8*0.3) | S8: =MIN(100,MAX(0,AVERAGE('03_Factor_SubScores'!Q8:R8)+MIN(10,'06_MLR_Regression'!G8)+MIN(15,'07_VAR_Granger'!I8*3))) | T8: =MIN(100,MAX(0,'03_Factor_SubScores'!S8*0.3+'03_Factor_SubScores'!T8*0.7)) | U8: =MIN(100,MAX(0,AVERAGE('03_Factor_SubScores'!U8:W8)))
A9: ='03_Factor_SubScores'!A9 | B9: ='03_Factor_SubScores'!B9 | C9: =ROUND(P9,2) | D9: =ROUND(Q9,2) | E9: =ROUND(R9,2) | F9: =ROUND(S9,2) | G9: =ROUND(T9,2) | H9: =ROUND(U9,2) | I9: =ROUND(P9*'01_Model_Config'!$C$6,2) | J9: =ROUND(Q9*'01_Model_Config'!$C$7,2) | K9: =ROUND(R9*'01_Model_Config'!$C$8,2) | L9: =ROUND(S9*'01_Model_Config'!$C$9,2) | M9: =ROUND(T9*'01_Model_Config'!$C$10,2) | N9: =ROUND(U9*'01_Model_Config'!$C$11,2) | O9: =SUM(I9:N9) | P9: =AVERAGE('03_Factor_SubScores'!C9:G9) | Q9: =IF('02_Market_Inputs'!O9<-2,MIN(20,IF('02_Market_Inputs'!P9>0,AVERAGE('03_Factor_SubScores'!H9:L9),AVERAGE('03_Factor_SubScores'!H9:K9))),IF('02_Market_Inputs'!P9>0,AVERAGE('03_Factor_SubScores'!H9:L9),AVERAGE('03_Factor_SubScores'!H9:K9))) | R9: =IF(ISBLANK('02_Market_Inputs'!U9),AVERAGE('03_Factor_SubScores'!M9:P9),AVERAGE('03_Factor_SubScores'!M9:P9)*0.7+'02_Market_Inputs'!U9*0.3) | S9: =MIN(100,MAX(0,AVERAGE('03_Factor_SubScores'!Q9:R9)+MIN(10,'06_MLR_Regression'!G9)+MIN(15,'07_VAR_Granger'!I9*3))) | T9: =MIN(100,MAX(0,'03_Factor_SubScores'!S9*0.3+'03_Factor_SubScores'!T9*0.7)) | U9: =MIN(100,MAX(0,AVERAGE('03_Factor_SubScores'!U9:W9)))
A10: ='03_Factor_SubScores'!A10 | B10: ='03_Factor_SubScores'!B10 | C10: =ROUND(P10,2) | D10: =ROUND(Q10,2) | E10: =ROUND(R10,2) | F10: =ROUND(S10,2) | G10: =ROUND(T10,2) | H10: =ROUND(U10,2) | I10: =ROUND(P10*'01_Model_Config'!$C$6,2) | J10: =ROUND(Q10*'01_Model_Config'!$C$7,2) | K10: =ROUND(R10*'01_Model_Config'!$C$8,2) | L10: =ROUND(S10*'01_Model_Config'!$C$9,2) | M10: =ROUND(T10*'01_Model_Config'!$C$10,2) | N10: =ROUND(U10*'01_Model_Config'!$C$11,2) | O10: =SUM(I10:N10) | P10: =AVERAGE('03_Factor_SubScores'!C10:G10) | Q10: =IF('02_Market_Inputs'!O10<-2,MIN(20,IF('02_Market_Inputs'!P10>0,AVERAGE('03_Factor_SubScores'!H10:L10),AVERAGE('03_Factor_SubScores'!H10:K10))),IF('02_Market_Inputs'!P10>0,AVERAGE('03_Factor_SubScores'!H10:L10),AVERAGE('03_Factor_SubScores'!H10:K10))) | R10: =IF(ISBLANK('02_Market_Inputs'!U10),AVERAGE('03_Factor_SubScores'!M10:P10),AVERAGE('03_Factor_SubScores'!M10:P10)*0.7+'02_Market_Inputs'!U10*0.3) | S10: =MIN(100,MAX(0,AVERAGE('03_Factor_SubScores'!Q10:R10)+MIN(10,'06_MLR_Regression'!G10)+MIN(15,'07_VAR_Granger'!I10*3))) | T10: =MIN(100,MAX(0,'03_Factor_SubScores'!S10*0.3+'03_Factor_SubScores'!T10*0.7)) | U10: =MIN(100,MAX(0,AVERAGE('03_Factor_SubScores'!U10:W10)))
A11: ='03_Factor_SubScores'!A11 | B11: ='03_Factor_SubScores'!B11 | C11: =ROUND(P11,2) | D11: =ROUND(Q11,2) | E11: =ROUND(R11,2) | F11: =ROUND(S11,2) | G11: =ROUND(T11,2) | H11: =ROUND(U11,2) | I11: =ROUND(P11*'01_Model_Config'!$C$6,2) | J11: =ROUND(Q11*'01_Model_Config'!$C$7,2) | K11: =ROUND(R11*'01_Model_Config'!$C$8,2) | L11: =ROUND(S11*'01_Model_Config'!$C$9,2) | M11: =ROUND(T11*'01_Model_Config'!$C$10,2) | N11: =ROUND(U11*'01_Model_Config'!$C$11,2) | O11: =SUM(I11:N11) | P11: =AVERAGE('03_Factor_SubScores'!C11:G11) | Q11: =IF('02_Market_Inputs'!O11<-2,MIN(20,IF('02_Market_Inputs'!P11>0,AVERAGE('03_Factor_SubScores'!H11:L11),AVERAGE('03_Factor_SubScores'!H11:K11))),IF('02_Market_Inputs'!P11>0,AVERAGE('03_Factor_SubScores'!H11:L11),AVERAGE('03_Factor_SubScores'!H11:K11))) | R11: =IF(ISBLANK('02_Market_Inputs'!U11),AVERAGE('03_Factor_SubScores'!M11:P11),AVERAGE('03_Factor_SubScores'!M11:P11)*0.7+'02_Market_Inputs'!U11*0.3) | S11: =MIN(100,MAX(0,AVERAGE('03_Factor_SubScores'!Q11:R11)+MIN(10,'06_MLR_Regression'!G11)+MIN(15,'07_VAR_Granger'!I11*3))) | T11: =MIN(100,MAX(0,'03_Factor_SubScores'!S11*0.3+'03_Factor_SubScores'!T11*0.7)) | U11: =MIN(100,MAX(0,AVERAGE('03_Factor_SubScores'!U11:W11)))
A12: ='03_Factor_SubScores'!A12 | B12: ='03_Factor_SubScores'!B12 | C12: =ROUND(P12,2) | D12: =ROUND(Q12,2) | E12: =ROUND(R12,2) | F12: =ROUND(S12,2) | G12: =ROUND(T12,2) | H12: =ROUND(U12,2) | I12: =ROUND(P12*'01_Model_Config'!$C$6,2) | J12: =ROUND(Q12*'01_Model_Config'!$C$7,2) | K12: =ROUND(R12*'01_Model_Config'!$C$8,2) | L12: =ROUND(S12*'01_Model_Config'!$C$9,2) | M12: =ROUND(T12*'01_Model_Config'!$C$10,2) | N12: =ROUND(U12*'01_Model_Config'!$C$11,2) | O12: =SUM(I12:N12) | P12: =AVERAGE('03_Factor_SubScores'!C12:G12) | Q12: =IF('02_Market_Inputs'!O12<-2,MIN(20,IF('02_Market_Inputs'!P12>0,AVERAGE('03_Factor_SubScores'!H12:L12),AVERAGE('03_Factor_SubScores'!H12:K12))),IF('02_Market_Inputs'!P12>0,AVERAGE('03_Factor_SubScores'!H12:L12),AVERAGE('03_Factor_SubScores'!H12:K12))) | R12: =IF(ISBLANK('02_Market_Inputs'!U12),AVERAGE('03_Factor_SubScores'!M12:P12),AVERAGE('03_Factor_SubScores'!M12:P12)*0.7+'02_Market_Inputs'!U12*0.3) | S12: =MIN(100,MAX(0,AVERAGE('03_Factor_SubScores'!Q12:R12)+MIN(10,'06_MLR_Regression'!G12)+MIN(15,'07_VAR_Granger'!I12*3))) | T12: =MIN(100,MAX(0,'03_Factor_SubScores'!S12*0.3+'03_Factor_SubScores'!T12*0.7)) | U12: =MIN(100,MAX(0,AVERAGE('03_Factor_SubScores'!U12:W12)))
A13: ='03_Factor_SubScores'!A13 | B13: ='03_Factor_SubScores'!B13 | C13: =ROUND(P13,2) | D13: =ROUND(Q13,2) | E13: =ROUND(R13,2) | F13: =ROUND(S13,2) | G13: =ROUND(T13,2) | H13: =ROUND(U13,2) | I13: =ROUND(P13*'01_Model_Config'!$C$6,2) | J13: =ROUND(Q13*'01_Model_Config'!$C$7,2) | K13: =ROUND(R13*'01_Model_Config'!$C$8,2) | L13: =ROUND(S13*'01_Model_Config'!$C$9,2) | M13: =ROUND(T13*'01_Model_Config'!$C$10,2) | N13: =ROUND(U13*'01_Model_Config'!$C$11,2) | O13: =SUM(I13:N13) | P13: =AVERAGE('03_Factor_SubScores'!C13:G13) | Q13: =IF('02_Market_Inputs'!O13<-2,MIN(20,IF('02_Market_Inputs'!P13>0,AVERAGE('03_Factor_SubScores'!H13:L13),AVERAGE('03_Factor_SubScores'!H13:K13))),IF('02_Market_Inputs'!P13>0,AVERAGE('03_Factor_SubScores'!H13:L13),AVERAGE('03_Factor_SubScores'!H13:K13))) | R13: =IF(ISBLANK('02_Market_Inputs'!U13),AVERAGE('03_Factor_SubScores'!M13:P13),AVERAGE('03_Factor_SubScores'!M13:P13)*0.7+'02_Market_Inputs'!U13*0.3) | S13: =MIN(100,MAX(0,AVERAGE('03_Factor_SubScores'!Q13:R13)+MIN(10,'06_MLR_Regression'!G13)+MIN(15,'07_VAR_Granger'!I13*3))) | T13: =MIN(100,MAX(0,'03_Factor_SubScores'!S13*0.3+'03_Factor_SubScores'!T13*0.7)) | U13: =MIN(100,MAX(0,AVERAGE('03_Factor_SubScores'!U13:W13)))
A14: ='03_Factor_SubScores'!A14 | B14: ='03_Factor_SubScores'!B14 | C14: =ROUND(P14,2) | D14: =ROUND(Q14,2) | E14: =ROUND(R14,2) | F14: =ROUND(S14,2) | G14: =ROUND(T14,2) | H14: =ROUND(U14,2) | I14: =ROUND(P14*'01_Model_Config'!$C$6,2) | J14: =ROUND(Q14*'01_Model_Config'!$C$7,2) | K14: =ROUND(R14*'01_Model_Config'!$C$8,2) | L14: =ROUND(S14*'01_Model_Config'!$C$9,2) | M14: =ROUND(T14*'01_Model_Config'!$C$10,2) | N14: =ROUND(U14*'01_Model_Config'!$C$11,2) | O14: =SUM(I14:N14) | P14: =AVERAGE('03_Factor_SubScores'!C14:G14) | Q14: =IF('02_Market_Inputs'!O14<-2,MIN(20,IF('02_Market_Inputs'!P14>0,AVERAGE('03_Factor_SubScores'!H14:L14),AVERAGE('03_Factor_SubScores'!H14:K14))),IF('02_Market_Inputs'!P14>0,AVERAGE('03_Factor_SubScores'!H14:L14),AVERAGE('03_Factor_SubScores'!H14:K14))) | R14: =IF(ISBLANK('02_Market_Inputs'!U14),AVERAGE('03_Factor_SubScores'!M14:P14),AVERAGE('03_Factor_SubScores'!M14:P14)*0.7+'02_Market_Inputs'!U14*0.3) | S14: =MIN(100,MAX(0,AVERAGE('03_Factor_SubScores'!Q14:R14)+MIN(10,'06_MLR_Regression'!G14)+MIN(15,'07_VAR_Granger'!I14*3))) | T14: =MIN(100,MAX(0,'03_Factor_SubScores'!S14*0.3+'03_Factor_SubScores'!T14*0.7)) | U14: =MIN(100,MAX(0,AVERAGE('03_Factor_SubScores'!U14:W14)))
A15: ='03_Factor_SubScores'!A15 | B15: ='03_Factor_SubScores'!B15 | C15: =ROUND(P15,2) | D15: =ROUND(Q15,2) | E15: =ROUND(R15,2) | F15: =ROUND(S15,2) | G15: =ROUND(T15,2) | H15: =ROUND(U15,2) | I15: =ROUND(P15*'01_Model_Config'!$C$6,2) | J15: =ROUND(Q15*'01_Model_Config'!$C$7,2) | K15: =ROUND(R15*'01_Model_Config'!$C$8,2) | L15: =ROUND(S15*'01_Model_Config'!$C$9,2) | M15: =ROUND(T15*'01_Model_Config'!$C$10,2) | N15: =ROUND(U15*'01_Model_Config'!$C$11,2) | O15: =SUM(I15:N15) | P15: =AVERAGE('03_Factor_SubScores'!C15:G15) | Q15: =IF('02_Market_Inputs'!O15<-2,MIN(20,IF('02_Market_Inputs'!P15>0,AVERAGE('03_Factor_SubScores'!H15:L15),AVERAGE('03_Factor_SubScores'!H15:K15))),IF('02_Market_Inputs'!P15>0,AVERAGE('03_Factor_SubScores'!H15:L15),AVERAGE('03_Factor_SubScores'!H15:K15))) | R15: =IF(ISBLANK('02_Market_Inputs'!U15),AVERAGE('03_Factor_SubScores'!M15:P15),AVERAGE('03_Factor_SubScores'!M15:P15)*0.7+'02_Market_Inputs'!U15*0.3) | S15: =MIN(100,MAX(0,AVERAGE('03_Factor_SubScores'!Q15:R15)+MIN(10,'06_MLR_Regression'!G15)+MIN(15,'07_VAR_Granger'!I15*3))) | T15: =MIN(100,MAX(0,'03_Factor_SubScores'!S15*0.3+'03_Factor_SubScores'!T15*0.7)) | U15: =MIN(100,MAX(0,AVERAGE('03_Factor_SubScores'!U15:W15)))
A16: ='03_Factor_SubScores'!A16 | B16: ='03_Factor_SubScores'!B16 | C16: =ROUND(P16,2) | D16: =ROUND(Q16,2) | E16: =ROUND(R16,2) | F16: =ROUND(S16,2) | G16: =ROUND(T16,2) | H16: =ROUND(U16,2) | I16: =ROUND(P16*'01_Model_Config'!$C$6,2) | J16: =ROUND(Q16*'01_Model_Config'!$C$7,2) | K16: =ROUND(R16*'01_Model_Config'!$C$8,2) | L16: =ROUND(S16*'01_Model_Config'!$C$9,2) | M16: =ROUND(T16*'01_Model_Config'!$C$10,2) | N16: =ROUND(U16*'01_Model_Config'!$C$11,2) | O16: =SUM(I16:N16) | P16: =AVERAGE('03_Factor_SubScores'!C16:G16) | Q16: =IF('02_Market_Inputs'!O16<-2,MIN(20,IF('02_Market_Inputs'!P16>0,AVERAGE('03_Factor_SubScores'!H16:L16),AVERAGE('03_Factor_SubScores'!H16:K16))),IF('02_Market_Inputs'!P16>0,AVERAGE('03_Factor_SubScores'!H16:L16),AVERAGE('03_Factor_SubScores'!H16:K16))) | R16: =IF(ISBLANK('02_Market_Inputs'!U16),AVERAGE('03_Factor_SubScores'!M16:P16),AVERAGE('03_Factor_SubScores'!M16:P16)*0.7+'02_Market_Inputs'!U16*0.3) | S16: =MIN(100,MAX(0,AVERAGE('03_Factor_SubScores'!Q16:R16)+MIN(10,'06_MLR_Regression'!G16)+MIN(15,'07_VAR_Granger'!I16*3))) | T16: =MIN(100,MAX(0,'03_Factor_SubScores'!S16*0.3+'03_Factor_SubScores'!T16*0.7)) | U16: =MIN(100,MAX(0,AVERAGE('03_Factor_SubScores'!U16:W16)))
... A28: ='03_Factor_SubScores'!A28 | B28: ='03_Factor_SubScores'!B28 | C28: =ROUND(P28,2) | D28: =ROUND(Q28,2) | E28: =ROUND(R28,2) | F28: =ROUND(S28,2) | G28: =ROUND(T28,2) | H28: =ROUND(U28,2) | I28: =ROUND(P28*'01_Model_Config'!$C$6,2) | J28: =ROUND(Q28*'01_Model_Config'!$C$7,2) | K28: =ROUND(R28*'01_Model_Config'!$C$8,2) | L28: =ROUND(S28*'01_Model_Config'!$C$9,2) | M28: =ROUND(T28*'01_Model_Config'!$C$10,2) | N28: =ROUND(U28*'01_Model_Config'!$C$11,2) | O28: =SUM(I28:N28) | P28: =AVERAGE('03_Factor_SubScores'!C28:G28) | Q28: =IF('02_Market_Inputs'!O28<-2,MIN(20,IF('02_Market_Inputs'!P28>0,AVERAGE('03_Factor_SubScores'!H28:L28),AVERAGE('03_Factor_SubScores'!H28:K28))),IF('02_Market_Inputs'!P28>0,AVERAGE('03_Factor_SubScores'!H28:L28),AVERAGE('03_Factor_SubScores'!H28:K28))) | R28: =IF(ISBLANK('02_Market_Inputs'!U28),AVERAGE('03_Factor_SubScores'!M28:P28),AVERAGE('03_Factor_SubScores'!M28:P28)*0.7+'02_Market_Inputs'!U28*0.3) | S28: =MIN(100,MAX(0,AVERAGE('03_Factor_SubScores'!Q28:R28)+MIN(10,'06_MLR_Regression'!G28)+MIN(15,'07_VAR_Granger'!I28*3))) | T28: =MIN(100,MAX(0,'03_Factor_SubScores'!S28*0.3+'03_Factor_SubScores'!T28*0.7)) | U28: =MIN(100,MAX(0,AVERAGE('03_Factor_SubScores'!U28:W28)))

Sheet 05_Composite_Calibration
A1: TWO-TIER COMPOSITE & EXPANDING CALIBRATION (v2)
A2: N<4: calibrated = raw | N≥4: σeff=MAX(σprior, min_std)·z capped ±z_cap·cal = clip(50+15×z_eff, Raw∓max_dist, 0..100); prior quarters only
A4: Quarter | B4: As-of Date | C4: As-of Close | D4: Raw Score | E4: Raw Label | F4: Prior N | G4: Prior Mean | H4: Prior Std | I4: Z-Score | J4: Calibrated Score | K4: Calibrated Label | L4: Suggested Allocation | M4: Pillar Std | N4: Pillar Range | O4: Dispersion | P4: Percentile Label | Q4: P15 Prior | R4: P85 Prior | S4: Rounded Raw Rank Key
A5: ='04_Pillar_Calculation'!A5 | B5: ='04_Pillar_Calculation'!B5 | C5: ='02_Market_Inputs'!C5 | D5: ='04_Pillar_Calculation'!O5 | E5: =IF(D5>='01_Model_Config'!$A$16,'01_Model_Config'!$C$16,IF(D5>='01_Model_Config'!$A$17,'01_Model_Config'!$C$17,IF(D5>='01_Model_Config'!$A$18,'01_Model_Config'!$C$18,IF(D5>='01_Model_Config'!$A$19,'01_Model_Config'!$C$19,'01_Model_Config'!$C$20)))) | F5: =ROWS($D$5:D5)-1 | G5: =IF(F5<'01_Model_Config'!$B$26,"","") | H5: =IF(F5<'01_Model_Config'!$B$26,"","") | I5: =IF(F5<'01_Model_Config'!$B$26,"",MIN('01_Model_Config'!$B$41,MAX(-'01_Model_Config'!$B$41,(D5-G5)/MAX(H5,'01_Model_Config'!$B$40)))) | J5: =ROUND(IF(F5<'01_Model_Config'!$B$26,D5,MIN('01_Model_Config'!$B$28,MAX('01_Model_Config'!$B$27,MIN(D5+'01_Model_Config'!$B$42,MAX(D5-'01_Model_Config'!$B$42,'01_Model_Config'!$B$24+'01_Model_Config'!$B$25*I5))))),2) | K5: =IF(J5>='01_Model_Config'!$A$16,'01_Model_Config'!$C$16,IF(J5>='01_Model_Config'!$A$17,'01_Model_Config'!$C$17,IF(J5>='01_Model_Config'!$A$18,'01_Model_Config'!$C$18,IF(J5>='01_Model_Config'!$A$19,'01_Model_Config'!$C$19,'01_Model_Config'!$C$20)))) | L5: =IF(J5>='01_Model_Config'!$A$16,'01_Model_Config'!$E$16,IF(J5>='01_Model_Config'!$A$17,'01_Model_Config'!$E$17,IF(J5>='01_Model_Config'!$A$18,'01_Model_Config'!$E$18,IF(J5>='01_Model_Config'!$A$19,'01_Model_Config'!$E$19,'01_Model_Config'!$E$20)))) | M5: =ROUND(STDEV.S('04_Pillar_Calculation'!C5:H5),2) | N5: =ROUND(MAX('04_Pillar_Calculation'!C5:H5)-MIN('04_Pillar_Calculation'!C5:H5),2) | O5: ="MEDIUM" | P5: ="HOLD" | Q5: =IF(F5<'01_Model_Config'!$B$26,"","") | R5: =IF(F5<'01_Model_Config'!$B$26,"","") | S5: =ROUND(D5,2)
A6: ='04_Pillar_Calculation'!A6 | B6: ='04_Pillar_Calculation'!B6 | C6: ='02_Market_Inputs'!C6 | D6: ='04_Pillar_Calculation'!O6 | E6: =IF(D6>='01_Model_Config'!$A$16,'01_Model_Config'!$C$16,IF(D6>='01_Model_Config'!$A$17,'01_Model_Config'!$C$17,IF(D6>='01_Model_Config'!$A$18,'01_Model_Config'!$C$18,IF(D6>='01_Model_Config'!$A$19,'01_Model_Config'!$C$19,'01_Model_Config'!$C$20)))) | F6: =ROWS($D$5:D6)-1 | G6: =IF(F6<'01_Model_Config'!$B$26,"",AVERAGE($D$5:D5)) | H6: =IF(F6<'01_Model_Config'!$B$26,"",STDEV.S($D$5:D5)) | I6: =IF(F6<'01_Model_Config'!$B$26,"",MIN('01_Model_Config'!$B$41,MAX(-'01_Model_Config'!$B$41,(D6-G6)/MAX(H6,'01_Model_Config'!$B$40)))) | J6: =ROUND(IF(F6<'01_Model_Config'!$B$26,D6,MIN('01_Model_Config'!$B$28,MAX('01_Model_Config'!$B$27,MIN(D6+'01_Model_Config'!$B$42,MAX(D6-'01_Model_Config'!$B$42,'01_Model_Config'!$B$24+'01_Model_Config'!$B$25*I6))))),2) | K6: =IF(J6>='01_Model_Config'!$A$16,'01_Model_Config'!$C$16,IF(J6>='01_Model_Config'!$A$17,'01_Model_Config'!$C$17,IF(J6>='01_Model_Config'!$A$18,'01_Model_Config'!$C$18,IF(J6>='01_Model_Config'!$A$19,'01_Model_Config'!$C$19,'01_Model_Config'!$C$20)))) | L6: =IF(J6>='01_Model_Config'!$A$16,'01_Model_Config'!$E$16,IF(J6>='01_Model_Config'!$A$17,'01_Model_Config'!$E$17,IF(J6>='01_Model_Config'!$A$18,'01_Model_Config'!$E$18,IF(J6>='01_Model_Config'!$A$19,'01_Model_Config'!$E$19,'01_Model_Config'!$E$20)))) | M6: =ROUND(STDEV.S('04_Pillar_Calculation'!C6:H6),2) | N6: =ROUND(MAX('04_Pillar_Calculation'!C6:H6)-MIN('04_Pillar_Calculation'!C6:H6),2) | O6: =IF(F6<'01_Model_Config'!$B$26,"MEDIUM",IF(M6>=PERCENTILE.INC($M$5:M5,0.67),"HIGH",IF(M6<=PERCENTILE.INC($M$5:M5,0.33),"LOW","MEDIUM"))) | P6: =IF(F6<'01_Model_Config'!$B$26,"HOLD",IF(D6>=R6,"BUY/ACCUMULATE",IF(D6<=Q6,"REDUCE/SELL","HOLD"))) | Q6: =IF(F6<'01_Model_Config'!$B$26,"",PERCENTILE.INC($D$5:D5,0.15)) | R6: =IF(F6<'01_Model_Config'!$B$26,"",PERCENTILE.INC($D$5:D5,0.85)) | S6: =ROUND(D6,2)
A7: ='04_Pillar_Calculation'!A7 | B7: ='04_Pillar_Calculation'!B7 | C7: ='02_Market_Inputs'!C7 | D7: ='04_Pillar_Calculation'!O7 | E7: =IF(D7>='01_Model_Config'!$A$16,'01_Model_Config'!$C$16,IF(D7>='01_Model_Config'!$A$17,'01_Model_Config'!$C$17,IF(D7>='01_Model_Config'!$A$18,'01_Model_Config'!$C$18,IF(D7>='01_Model_Config'!$A$19,'01_Model_Config'!$C$19,'01_Model_Config'!$C$20)))) | F7: =ROWS($D$5:D7)-1 | G7: =IF(F7<'01_Model_Config'!$B$26,"",AVERAGE($D$5:D6)) | H7: =IF(F7<'01_Model_Config'!$B$26,"",STDEV.S($D$5:D6)) | I7: =IF(F7<'01_Model_Config'!$B$26,"",MIN('01_Model_Config'!$B$41,MAX(-'01_Model_Config'!$B$41,(D7-G7)/MAX(H7,'01_Model_Config'!$B$40)))) | J7: =ROUND(IF(F7<'01_Model_Config'!$B$26,D7,MIN('01_Model_Config'!$B$28,MAX('01_Model_Config'!$B$27,MIN(D7+'01_Model_Config'!$B$42,MAX(D7-'01_Model_Config'!$B$42,'01_Model_Config'!$B$24+'01_Model_Config'!$B$25*I7))))),2) | K7: =IF(J7>='01_Model_Config'!$A$16,'01_Model_Config'!$C$16,IF(J7>='01_Model_Config'!$A$17,'01_Model_Config'!$C$17,IF(J7>='01_Model_Config'!$A$18,'01_Model_Config'!$C$18,IF(J7>='01_Model_Config'!$A$19,'01_Model_Config'!$C$19,'01_Model_Config'!$C$20)))) | L7: =IF(J7>='01_Model_Config'!$A$16,'01_Model_Config'!$E$16,IF(J7>='01_Model_Config'!$A$17,'01_Model_Config'!$E$17,IF(J7>='01_Model_Config'!$A$18,'01_Model_Config'!$E$18,IF(J7>='01_Model_Config'!$A$19,'01_Model_Config'!$E$19,'01_Model_Config'!$E$20)))) | M7: =ROUND(STDEV.S('04_Pillar_Calculation'!C7:H7),2) | N7: =ROUND(MAX('04_Pillar_Calculation'!C7:H7)-MIN('04_Pillar_Calculation'!C7:H7),2) | O7: =IF(F7<'01_Model_Config'!$B$26,"MEDIUM",IF(M7>=PERCENTILE.INC($M$5:M6,0.67),"HIGH",IF(M7<=PERCENTILE.INC($M$5:M6,0.33),"LOW","MEDIUM"))) | P7: =IF(F7<'01_Model_Config'!$B$26,"HOLD",IF(D7>=R7,"BUY/ACCUMULATE",IF(D7<=Q7,"REDUCE/SELL","HOLD"))) | Q7: =IF(F7<'01_Model_Config'!$B$26,"",PERCENTILE.INC($D$5:D6,0.15)) | R7: =IF(F7<'01_Model_Config'!$B$26,"",PERCENTILE.INC($D$5:D6,0.85)) | S7: =ROUND(D7,2)
A8: ='04_Pillar_Calculation'!A8 | B8: ='04_Pillar_Calculation'!B8 | C8: ='02_Market_Inputs'!C8 | D8: ='04_Pillar_Calculation'!O8 | E8: =IF(D8>='01_Model_Config'!$A$16,'01_Model_Config'!$C$16,IF(D8>='01_Model_Config'!$A$17,'01_Model_Config'!$C$17,IF(D8>='01_Model_Config'!$A$18,'01_Model_Config'!$C$18,IF(D8>='01_Model_Config'!$A$19,'01_Model_Config'!$C$19,'01_Model_Config'!$C$20)))) | F8: =ROWS($D$5:D8)-1 | G8: =IF(F8<'01_Model_Config'!$B$26,"",AVERAGE($D$5:D7)) | H8: =IF(F8<'01_Model_Config'!$B$26,"",STDEV.S($D$5:D7)) | I8: =IF(F8<'01_Model_Config'!$B$26,"",MIN('01_Model_Config'!$B$41,MAX(-'01_Model_Config'!$B$41,(D8-G8)/MAX(H8,'01_Model_Config'!$B$40)))) | J8: =ROUND(IF(F8<'01_Model_Config'!$B$26,D8,MIN('01_Model_Config'!$B$28,MAX('01_Model_Config'!$B$27,MIN(D8+'01_Model_Config'!$B$42,MAX(D8-'01_Model_Config'!$B$42,'01_Model_Config'!$B$24+'01_Model_Config'!$B$25*I8))))),2) | K8: =IF(J8>='01_Model_Config'!$A$16,'01_Model_Config'!$C$16,IF(J8>='01_Model_Config'!$A$17,'01_Model_Config'!$C$17,IF(J8>='01_Model_Config'!$A$18,'01_Model_Config'!$C$18,IF(J8>='01_Model_Config'!$A$19,'01_Model_Config'!$C$19,'01_Model_Config'!$C$20)))) | L8: =IF(J8>='01_Model_Config'!$A$16,'01_Model_Config'!$E$16,IF(J8>='01_Model_Config'!$A$17,'01_Model_Config'!$E$17,IF(J8>='01_Model_Config'!$A$18,'01_Model_Config'!$E$18,IF(J8>='01_Model_Config'!$A$19,'01_Model_Config'!$E$19,'01_Model_Config'!$E$20)))) | M8: =ROUND(STDEV.S('04_Pillar_Calculation'!C8:H8),2) | N8: =ROUND(MAX('04_Pillar_Calculation'!C8:H8)-MIN('04_Pillar_Calculation'!C8:H8),2) | O8: =IF(F8<'01_Model_Config'!$B$26,"MEDIUM",IF(M8>=PERCENTILE.INC($M$5:M7,0.67),"HIGH",IF(M8<=PERCENTILE.INC($M$5:M7,0.33),"LOW","MEDIUM"))) | P8: =IF(F8<'01_Model_Config'!$B$26,"HOLD",IF(D8>=R8,"BUY/ACCUMULATE",IF(D8<=Q8,"REDUCE/SELL","HOLD"))) | Q8: =IF(F8<'01_Model_Config'!$B$26,"",PERCENTILE.INC($D$5:D7,0.15)) | R8: =IF(F8<'01_Model_Config'!$B$26,"",PERCENTILE.INC($D$5:D7,0.85)) | S8: =ROUND(D8,2)
A9: ='04_Pillar_Calculation'!A9 | B9: ='04_Pillar_Calculation'!B9 | C9: ='02_Market_Inputs'!C9 | D9: ='04_Pillar_Calculation'!O9 | E9: =IF(D9>='01_Model_Config'!$A$16,'01_Model_Config'!$C$16,IF(D9>='01_Model_Config'!$A$17,'01_Model_Config'!$C$17,IF(D9>='01_Model_Config'!$A$18,'01_Model_Config'!$C$18,IF(D9>='01_Model_Config'!$A$19,'01_Model_Config'!$C$19,'01_Model_Config'!$C$20)))) | F9: =ROWS($D$5:D9)-1 | G9: =IF(F9<'01_Model_Config'!$B$26,"",AVERAGE($D$5:D8)) | H9: =IF(F9<'01_Model_Config'!$B$26,"",STDEV.S($D$5:D8)) | I9: =IF(F9<'01_Model_Config'!$B$26,"",MIN('01_Model_Config'!$B$41,MAX(-'01_Model_Config'!$B$41,(D9-G9)/MAX(H9,'01_Model_Config'!$B$40)))) | J9: =ROUND(IF(F9<'01_Model_Config'!$B$26,D9,MIN('01_Model_Config'!$B$28,MAX('01_Model_Config'!$B$27,MIN(D9+'01_Model_Config'!$B$42,MAX(D9-'01_Model_Config'!$B$42,'01_Model_Config'!$B$24+'01_Model_Config'!$B$25*I9))))),2) | K9: =IF(J9>='01_Model_Config'!$A$16,'01_Model_Config'!$C$16,IF(J9>='01_Model_Config'!$A$17,'01_Model_Config'!$C$17,IF(J9>='01_Model_Config'!$A$18,'01_Model_Config'!$C$18,IF(J9>='01_Model_Config'!$A$19,'01_Model_Config'!$C$19,'01_Model_Config'!$C$20)))) | L9: =IF(J9>='01_Model_Config'!$A$16,'01_Model_Config'!$E$16,IF(J9>='01_Model_Config'!$A$17,'01_Model_Config'!$E$17,IF(J9>='01_Model_Config'!$A$18,'01_Model_Config'!$E$18,IF(J9>='01_Model_Config'!$A$19,'01_Model_Config'!$E$19,'01_Model_Config'!$E$20)))) | M9: =ROUND(STDEV.S('04_Pillar_Calculation'!C9:H9),2) | N9: =ROUND(MAX('04_Pillar_Calculation'!C9:H9)-MIN('04_Pillar_Calculation'!C9:H9),2) | O9: =IF(F9<'01_Model_Config'!$B$26,"MEDIUM",IF(M9>=PERCENTILE.INC($M$5:M8,0.67),"HIGH",IF(M9<=PERCENTILE.INC($M$5:M8,0.33),"LOW","MEDIUM"))) | P9: =IF(F9<'01_Model_Config'!$B$26,"HOLD",IF(D9>=R9,"BUY/ACCUMULATE",IF(D9<=Q9,"REDUCE/SELL","HOLD"))) | Q9: =IF(F9<'01_Model_Config'!$B$26,"",PERCENTILE.INC($D$5:D8,0.15)) | R9: =IF(F9<'01_Model_Config'!$B$26,"",PERCENTILE.INC($D$5:D8,0.85)) | S9: =ROUND(D9,2)
A10: ='04_Pillar_Calculation'!A10 | B10: ='04_Pillar_Calculation'!B10 | C10: ='02_Market_Inputs'!C10 | D10: ='04_Pillar_Calculation'!O10 | E10: =IF(D10>='01_Model_Config'!$A$16,'01_Model_Config'!$C$16,IF(D10>='01_Model_Config'!$A$17,'01_Model_Config'!$C$17,IF(D10>='01_Model_Config'!$A$18,'01_Model_Config'!$C$18,IF(D10>='01_Model_Config'!$A$19,'01_Model_Config'!$C$19,'01_Model_Config'!$C$20)))) | F10: =ROWS($D$5:D10)-1 | G10: =IF(F10<'01_Model_Config'!$B$26,"",AVERAGE($D$5:D9)) | H10: =IF(F10<'01_Model_Config'!$B$26,"",STDEV.S($D$5:D9)) | I10: =IF(F10<'01_Model_Config'!$B$26,"",MIN('01_Model_Config'!$B$41,MAX(-'01_Model_Config'!$B$41,(D10-G10)/MAX(H10,'01_Model_Config'!$B$40)))) | J10: =ROUND(IF(F10<'01_Model_Config'!$B$26,D10,MIN('01_Model_Config'!$B$28,MAX('01_Model_Config'!$B$27,MIN(D10+'01_Model_Config'!$B$42,MAX(D10-'01_Model_Config'!$B$42,'01_Model_Config'!$B$24+'01_Model_Config'!$B$25*I10))))),2) | K10: =IF(J10>='01_Model_Config'!$A$16,'01_Model_Config'!$C$16,IF(J10>='01_Model_Config'!$A$17,'01_Model_Config'!$C$17,IF(J10>='01_Model_Config'!$A$18,'01_Model_Config'!$C$18,IF(J10>='01_Model_Config'!$A$19,'01_Model_Config'!$C$19,'01_Model_Config'!$C$20)))) | L10: =IF(J10>='01_Model_Config'!$A$16,'01_Model_Config'!$E$16,IF(J10>='01_Model_Config'!$A$17,'01_Model_Config'!$E$17,IF(J10>='01_Model_Config'!$A$18,'01_Model_Config'!$E$18,IF(J10>='01_Model_Config'!$A$19,'01_Model_Config'!$E$19,'01_Model_Config'!$E$20)))) | M10: =ROUND(STDEV.S('04_Pillar_Calculation'!C10:H10),2) | N10: =ROUND(MAX('04_Pillar_Calculation'!C10:H10)-MIN('04_Pillar_Calculation'!C10:H10),2) | O10: =IF(F10<'01_Model_Config'!$B$26,"MEDIUM",IF(M10>=PERCENTILE.INC($M$5:M9,0.67),"HIGH",IF(M10<=PERCENTILE.INC($M$5:M9,0.33),"LOW","MEDIUM"))) | P10: =IF(F10<'01_Model_Config'!$B$26,"HOLD",IF(D10>=R10,"BUY/ACCUMULATE",IF(D10<=Q10,"REDUCE/SELL","HOLD"))) | Q10: =IF(F10<'01_Model_Config'!$B$26,"",PERCENTILE.INC($D$5:D9,0.15)) | R10: =IF(F10<'01_Model_Config'!$B$26,"",PERCENTILE.INC($D$5:D9,0.85)) | S10: =ROUND(D10,2)
A11: ='04_Pillar_Calculation'!A11 | B11: ='04_Pillar_Calculation'!B11 | C11: ='02_Market_Inputs'!C11 | D11: ='04_Pillar_Calculation'!O11 | E11: =IF(D11>='01_Model_Config'!$A$16,'01_Model_Config'!$C$16,IF(D11>='01_Model_Config'!$A$17,'01_Model_Config'!$C$17,IF(D11>='01_Model_Config'!$A$18,'01_Model_Config'!$C$18,IF(D11>='01_Model_Config'!$A$19,'01_Model_Config'!$C$19,'01_Model_Config'!$C$20)))) | F11: =ROWS($D$5:D11)-1 | G11: =IF(F11<'01_Model_Config'!$B$26,"",AVERAGE($D$5:D10)) | H11: =IF(F11<'01_Model_Config'!$B$26,"",STDEV.S($D$5:D10)) | I11: =IF(F11<'01_Model_Config'!$B$26,"",MIN('01_Model_Config'!$B$41,MAX(-'01_Model_Config'!$B$41,(D11-G11)/MAX(H11,'01_Model_Config'!$B$40)))) | J11: =ROUND(IF(F11<'01_Model_Config'!$B$26,D11,MIN('01_Model_Config'!$B$28,MAX('01_Model_Config'!$B$27,MIN(D11+'01_Model_Config'!$B$42,MAX(D11-'01_Model_Config'!$B$42,'01_Model_Config'!$B$24+'01_Model_Config'!$B$25*I11))))),2) | K11: =IF(J11>='01_Model_Config'!$A$16,'01_Model_Config'!$C$16,IF(J11>='01_Model_Config'!$A$17,'01_Model_Config'!$C$17,IF(J11>='01_Model_Config'!$A$18,'01_Model_Config'!$C$18,IF(J11>='01_Model_Config'!$A$19,'01_Model_Config'!$C$19,'01_Model_Config'!$C$20)))) | L11: =IF(J11>='01_Model_Config'!$A$16,'01_Model_Config'!$E$16,IF(J11>='01_Model_Config'!$A$17,'01_Model_Config'!$E$17,IF(J11>='01_Model_Config'!$A$18,'01_Model_Config'!$E$18,IF(J11>='01_Model_Config'!$A$19,'01_Model_Config'!$E$19,'01_Model_Config'!$E$20)))) | M11: =ROUND(STDEV.S('04_Pillar_Calculation'!C11:H11),2) | N11: =ROUND(MAX('04_Pillar_Calculation'!C11:H11)-MIN('04_Pillar_Calculation'!C11:H11),2) | O11: =IF(F11<'01_Model_Config'!$B$26,"MEDIUM",IF(M11>=PERCENTILE.INC($M$5:M10,0.67),"HIGH",IF(M11<=PERCENTILE.INC($M$5:M10,0.33),"LOW","MEDIUM"))) | P11: =IF(F11<'01_Model_Config'!$B$26,"HOLD",IF(D11>=R11,"BUY/ACCUMULATE",IF(D11<=Q11,"REDUCE/SELL","HOLD"))) | Q11: =IF(F11<'01_Model_Config'!$B$26,"",PERCENTILE.INC($D$5:D10,0.15)) | R11: =IF(F11<'01_Model_Config'!$B$26,"",PERCENTILE.INC($D$5:D10,0.85)) | S11: =ROUND(D11,2)
A12: ='04_Pillar_Calculation'!A12 | B12: ='04_Pillar_Calculation'!B12 | C12: ='02_Market_Inputs'!C12 | D12: ='04_Pillar_Calculation'!O12 | E12: =IF(D12>='01_Model_Config'!$A$16,'01_Model_Config'!$C$16,IF(D12>='01_Model_Config'!$A$17,'01_Model_Config'!$C$17,IF(D12>='01_Model_Config'!$A$18,'01_Model_Config'!$C$18,IF(D12>='01_Model_Config'!$A$19,'01_Model_Config'!$C$19,'01_Model_Config'!$C$20)))) | F12: =ROWS($D$5:D12)-1 | G12: =IF(F12<'01_Model_Config'!$B$26,"",AVERAGE($D$5:D11)) | H12: =IF(F12<'01_Model_Config'!$B$26,"",STDEV.S($D$5:D11)) | I12: =IF(F12<'01_Model_Config'!$B$26,"",MIN('01_Model_Config'!$B$41,MAX(-'01_Model_Config'!$B$41,(D12-G12)/MAX(H12,'01_Model_Config'!$B$40)))) | J12: =ROUND(IF(F12<'01_Model_Config'!$B$26,D12,MIN('01_Model_Config'!$B$28,MAX('01_Model_Config'!$B$27,MIN(D12+'01_Model_Config'!$B$42,MAX(D12-'01_Model_Config'!$B$42,'01_Model_Config'!$B$24+'01_Model_Config'!$B$25*I12))))),2) | K12: =IF(J12>='01_Model_Config'!$A$16,'01_Model_Config'!$C$16,IF(J12>='01_Model_Config'!$A$17,'01_Model_Config'!$C$17,IF(J12>='01_Model_Config'!$A$18,'01_Model_Config'!$C$18,IF(J12>='01_Model_Config'!$A$19,'01_Model_Config'!$C$19,'01_Model_Config'!$C$20)))) | L12: =IF(J12>='01_Model_Config'!$A$16,'01_Model_Config'!$E$16,IF(J12>='01_Model_Config'!$A$17,'01_Model_Config'!$E$17,IF(J12>='01_Model_Config'!$A$18,'01_Model_Config'!$E$18,IF(J12>='01_Model_Config'!$A$19,'01_Model_Config'!$E$19,'01_Model_Config'!$E$20)))) | M12: =ROUND(STDEV.S('04_Pillar_Calculation'!C12:H12),2) | N12: =ROUND(MAX('04_Pillar_Calculation'!C12:H12)-MIN('04_Pillar_Calculation'!C12:H12),2) | O12: =IF(F12<'01_Model_Config'!$B$26,"MEDIUM",IF(M12>=PERCENTILE.INC($M$5:M11,0.67),"HIGH",IF(M12<=PERCENTILE.INC($M$5:M11,0.33),"LOW","MEDIUM"))) | P12: =IF(F12<'01_Model_Config'!$B$26,"HOLD",IF(D12>=R12,"BUY/ACCUMULATE",IF(D12<=Q12,"REDUCE/SELL","HOLD"))) | Q12: =IF(F12<'01_Model_Config'!$B$26,"",PERCENTILE.INC($D$5:D11,0.15)) | R12: =IF(F12<'01_Model_Config'!$B$26,"",PERCENTILE.INC($D$5:D11,0.85)) | S12: =ROUND(D12,2)
A13: ='04_Pillar_Calculation'!A13 | B13: ='04_Pillar_Calculation'!B13 | C13: ='02_Market_Inputs'!C13 | D13: ='04_Pillar_Calculation'!O13 | E13: =IF(D13>='01_Model_Config'!$A$16,'01_Model_Config'!$C$16,IF(D13>='01_Model_Config'!$A$17,'01_Model_Config'!$C$17,IF(D13>='01_Model_Config'!$A$18,'01_Model_Config'!$C$18,IF(D13>='01_Model_Config'!$A$19,'01_Model_Config'!$C$19,'01_Model_Config'!$C$20)))) | F13: =ROWS($D$5:D13)-1 | G13: =IF(F13<'01_Model_Config'!$B$26,"",AVERAGE($D$5:D12)) | H13: =IF(F13<'01_Model_Config'!$B$26,"",STDEV.S($D$5:D12)) | I13: =IF(F13<'01_Model_Config'!$B$26,"",MIN('01_Model_Config'!$B$41,MAX(-'01_Model_Config'!$B$41,(D13-G13)/MAX(H13,'01_Model_Config'!$B$40)))) | J13: =ROUND(IF(F13<'01_Model_Config'!$B$26,D13,MIN('01_Model_Config'!$B$28,MAX('01_Model_Config'!$B$27,MIN(D13+'01_Model_Config'!$B$42,MAX(D13-'01_Model_Config'!$B$42,'01_Model_Config'!$B$24+'01_Model_Config'!$B$25*I13))))),2) | K13: =IF(J13>='01_Model_Config'!$A$16,'01_Model_Config'!$C$16,IF(J13>='01_Model_Config'!$A$17,'01_Model_Config'!$C$17,IF(J13>='01_Model_Config'!$A$18,'01_Model_Config'!$C$18,IF(J13>='01_Model_Config'!$A$19,'01_Model_Config'!$C$19,'01_Model_Config'!$C$20)))) | L13: =IF(J13>='01_Model_Config'!$A$16,'01_Model_Config'!$E$16,IF(J13>='01_Model_Config'!$A$17,'01_Model_Config'!$E$17,IF(J13>='01_Model_Config'!$A$18,'01_Model_Config'!$E$18,IF(J13>='01_Model_Config'!$A$19,'01_Model_Config'!$E$19,'01_Model_Config'!$E$20)))) | M13: =ROUND(STDEV.S('04_Pillar_Calculation'!C13:H13),2) | N13: =ROUND(MAX('04_Pillar_Calculation'!C13:H13)-MIN('04_Pillar_Calculation'!C13:H13),2) | O13: =IF(F13<'01_Model_Config'!$B$26,"MEDIUM",IF(M13>=PERCENTILE.INC($M$5:M12,0.67),"HIGH",IF(M13<=PERCENTILE.INC($M$5:M12,0.33),"LOW","MEDIUM"))) | P13: =IF(F13<'01_Model_Config'!$B$26,"HOLD",IF(D13>=R13,"BUY/ACCUMULATE",IF(D13<=Q13,"REDUCE/SELL","HOLD"))) | Q13: =IF(F13<'01_Model_Config'!$B$26,"",PERCENTILE.INC($D$5:D12,0.15)) | R13: =IF(F13<'01_Model_Config'!$B$26,"",PERCENTILE.INC($D$5:D12,0.85)) | S13: =ROUND(D13,2)
A14: ='04_Pillar_Calculation'!A14 | B14: ='04_Pillar_Calculation'!B14 | C14: ='02_Market_Inputs'!C14 | D14: ='04_Pillar_Calculation'!O14 | E14: =IF(D14>='01_Model_Config'!$A$16,'01_Model_Config'!$C$16,IF(D14>='01_Model_Config'!$A$17,'01_Model_Config'!$C$17,IF(D14>='01_Model_Config'!$A$18,'01_Model_Config'!$C$18,IF(D14>='01_Model_Config'!$A$19,'01_Model_Config'!$C$19,'01_Model_Config'!$C$20)))) | F14: =ROWS($D$5:D14)-1 | G14: =IF(F14<'01_Model_Config'!$B$26,"",AVERAGE($D$5:D13)) | H14: =IF(F14<'01_Model_Config'!$B$26,"",STDEV.S($D$5:D13)) | I14: =IF(F14<'01_Model_Config'!$B$26,"",MIN('01_Model_Config'!$B$41,MAX(-'01_Model_Config'!$B$41,(D14-G14)/MAX(H14,'01_Model_Config'!$B$40)))) | J14: =ROUND(IF(F14<'01_Model_Config'!$B$26,D14,MIN('01_Model_Config'!$B$28,MAX('01_Model_Config'!$B$27,MIN(D14+'01_Model_Config'!$B$42,MAX(D14-'01_Model_Config'!$B$42,'01_Model_Config'!$B$24+'01_Model_Config'!$B$25*I14))))),2) | K14: =IF(J14>='01_Model_Config'!$A$16,'01_Model_Config'!$C$16,IF(J14>='01_Model_Config'!$A$17,'01_Model_Config'!$C$17,IF(J14>='01_Model_Config'!$A$18,'01_Model_Config'!$C$18,IF(J14>='01_Model_Config'!$A$19,'01_Model_Config'!$C$19,'01_Model_Config'!$C$20)))) | L14: =IF(J14>='01_Model_Config'!$A$16,'01_Model_Config'!$E$16,IF(J14>='01_Model_Config'!$A$17,'01_Model_Config'!$E$17,IF(J14>='01_Model_Config'!$A$18,'01_Model_Config'!$E$18,IF(J14>='01_Model_Config'!$A$19,'01_Model_Config'!$E$19,'01_Model_Config'!$E$20)))) | M14: =ROUND(STDEV.S('04_Pillar_Calculation'!C14:H14),2) | N14: =ROUND(MAX('04_Pillar_Calculation'!C14:H14)-MIN('04_Pillar_Calculation'!C14:H14),2) | O14: =IF(F14<'01_Model_Config'!$B$26,"MEDIUM",IF(M14>=PERCENTILE.INC($M$5:M13,0.67),"HIGH",IF(M14<=PERCENTILE.INC($M$5:M13,0.33),"LOW","MEDIUM"))) | P14: =IF(F14<'01_Model_Config'!$B$26,"HOLD",IF(D14>=R14,"BUY/ACCUMULATE",IF(D14<=Q14,"REDUCE/SELL","HOLD"))) | Q14: =IF(F14<'01_Model_Config'!$B$26,"",PERCENTILE.INC($D$5:D13,0.15)) | R14: =IF(F14<'01_Model_Config'!$B$26,"",PERCENTILE.INC($D$5:D13,0.85)) | S14: =ROUND(D14,2)
A15: ='04_Pillar_Calculation'!A15 | B15: ='04_Pillar_Calculation'!B15 | C15: ='02_Market_Inputs'!C15 | D15: ='04_Pillar_Calculation'!O15 | E15: =IF(D15>='01_Model_Config'!$A$16,'01_Model_Config'!$C$16,IF(D15>='01_Model_Config'!$A$17,'01_Model_Config'!$C$17,IF(D15>='01_Model_Config'!$A$18,'01_Model_Config'!$C$18,IF(D15>='01_Model_Config'!$A$19,'01_Model_Config'!$C$19,'01_Model_Config'!$C$20)))) | F15: =ROWS($D$5:D15)-1 | G15: =IF(F15<'01_Model_Config'!$B$26,"",AVERAGE($D$5:D14)) | H15: =IF(F15<'01_Model_Config'!$B$26,"",STDEV.S($D$5:D14)) | I15: =IF(F15<'01_Model_Config'!$B$26,"",MIN('01_Model_Config'!$B$41,MAX(-'01_Model_Config'!$B$41,(D15-G15)/MAX(H15,'01_Model_Config'!$B$40)))) | J15: =ROUND(IF(F15<'01_Model_Config'!$B$26,D15,MIN('01_Model_Config'!$B$28,MAX('01_Model_Config'!$B$27,MIN(D15+'01_Model_Config'!$B$42,MAX(D15-'01_Model_Config'!$B$42,'01_Model_Config'!$B$24+'01_Model_Config'!$B$25*I15))))),2) | K15: =IF(J15>='01_Model_Config'!$A$16,'01_Model_Config'!$C$16,IF(J15>='01_Model_Config'!$A$17,'01_Model_Config'!$C$17,IF(J15>='01_Model_Config'!$A$18,'01_Model_Config'!$C$18,IF(J15>='01_Model_Config'!$A$19,'01_Model_Config'!$C$19,'01_Model_Config'!$C$20)))) | L15: =IF(J15>='01_Model_Config'!$A$16,'01_Model_Config'!$E$16,IF(J15>='01_Model_Config'!$A$17,'01_Model_Config'!$E$17,IF(J15>='01_Model_Config'!$A$18,'01_Model_Config'!$E$18,IF(J15>='01_Model_Config'!$A$19,'01_Model_Config'!$E$19,'01_Model_Config'!$E$20)))) | M15: =ROUND(STDEV.S('04_Pillar_Calculation'!C15:H15),2) | N15: =ROUND(MAX('04_Pillar_Calculation'!C15:H15)-MIN('04_Pillar_Calculation'!C15:H15),2) | O15: =IF(F15<'01_Model_Config'!$B$26,"MEDIUM",IF(M15>=PERCENTILE.INC($M$5:M14,0.67),"HIGH",IF(M15<=PERCENTILE.INC($M$5:M14,0.33),"LOW","MEDIUM"))) | P15: =IF(F15<'01_Model_Config'!$B$26,"HOLD",IF(D15>=R15,"BUY/ACCUMULATE",IF(D15<=Q15,"REDUCE/SELL","HOLD"))) | Q15: =IF(F15<'01_Model_Config'!$B$26,"",PERCENTILE.INC($D$5:D14,0.15)) | R15: =IF(F15<'01_Model_Config'!$B$26,"",PERCENTILE.INC($D$5:D14,0.85)) | S15: =ROUND(D15,2)
A16: ='04_Pillar_Calculation'!A16 | B16: ='04_Pillar_Calculation'!B16 | C16: ='02_Market_Inputs'!C16 | D16: ='04_Pillar_Calculation'!O16 | E16: =IF(D16>='01_Model_Config'!$A$16,'01_Model_Config'!$C$16,IF(D16>='01_Model_Config'!$A$17,'01_Model_Config'!$C$17,IF(D16>='01_Model_Config'!$A$18,'01_Model_Config'!$C$18,IF(D16>='01_Model_Config'!$A$19,'01_Model_Config'!$C$19,'01_Model_Config'!$C$20)))) | F16: =ROWS($D$5:D16)-1 | G16: =IF(F16<'01_Model_Config'!$B$26,"",AVERAGE($D$5:D15)) | H16: =IF(F16<'01_Model_Config'!$B$26,"",STDEV.S($D$5:D15)) | I16: =IF(F16<'01_Model_Config'!$B$26,"",MIN('01_Model_Config'!$B$41,MAX(-'01_Model_Config'!$B$41,(D16-G16)/MAX(H16,'01_Model_Config'!$B$40)))) | J16: =ROUND(IF(F16<'01_Model_Config'!$B$26,D16,MIN('01_Model_Config'!$B$28,MAX('01_Model_Config'!$B$27,MIN(D16+'01_Model_Config'!$B$42,MAX(D16-'01_Model_Config'!$B$42,'01_Model_Config'!$B$24+'01_Model_Config'!$B$25*I16))))),2) | K16: =IF(J16>='01_Model_Config'!$A$16,'01_Model_Config'!$C$16,IF(J16>='01_Model_Config'!$A$17,'01_Model_Config'!$C$17,IF(J16>='01_Model_Config'!$A$18,'01_Model_Config'!$C$18,IF(J16>='01_Model_Config'!$A$19,'01_Model_Config'!$C$19,'01_Model_Config'!$C$20)))) | L16: =IF(J16>='01_Model_Config'!$A$16,'01_Model_Config'!$E$16,IF(J16>='01_Model_Config'!$A$17,'01_Model_Config'!$E$17,IF(J16>='01_Model_Config'!$A$18,'01_Model_Config'!$E$18,IF(J16>='01_Model_Config'!$A$19,'01_Model_Config'!$E$19,'01_Model_Config'!$E$20)))) | M16: =ROUND(STDEV.S('04_Pillar_Calculation'!C16:H16),2) | N16: =ROUND(MAX('04_Pillar_Calculation'!C16:H16)-MIN('04_Pillar_Calculation'!C16:H16),2) | O16: =IF(F16<'01_Model_Config'!$B$26,"MEDIUM",IF(M16>=PERCENTILE.INC($M$5:M15,0.67),"HIGH",IF(M16<=PERCENTILE.INC($M$5:M15,0.33),"LOW","MEDIUM"))) | P16: =IF(F16<'01_Model_Config'!$B$26,"HOLD",IF(D16>=R16,"BUY/ACCUMULATE",IF(D16<=Q16,"REDUCE/SELL","HOLD"))) | Q16: =IF(F16<'01_Model_Config'!$B$26,"",PERCENTILE.INC($D$5:D15,0.15)) | R16: =IF(F16<'01_Model_Config'!$B$26,"",PERCENTILE.INC($D$5:D15,0.85)) | S16: =ROUND(D16,2)
A17: ='04_Pillar_Calculation'!A17 | B17: ='04_Pillar_Calculation'!B17 | C17: ='02_Market_Inputs'!C17 | D17: ='04_Pillar_Calculation'!O17 | E17: =IF(D17>='01_Model_Config'!$A$16,'01_Model_Config'!$C$16,IF(D17>='01_Model_Config'!$A$17,'01_Model_Config'!$C$17,IF(D17>='01_Model_Config'!$A$18,'01_Model_Config'!$C$18,IF(D17>='01_Model_Config'!$A$19,'01_Model_Config'!$C$19,'01_Model_Config'!$C$20)))) | F17: =ROWS($D$5:D17)-1 | G17: =IF(F17<'01_Model_Config'!$B$26,"",AVERAGE($D$5:D16)) | H17: =IF(F17<'01_Model_Config'!$B$26,"",STDEV.S($D$5:D16)) | I17: =IF(F17<'01_Model_Config'!$B$26,"",MIN('01_Model_Config'!$B$41,MAX(-'01_Model_Config'!$B$41,(D17-G17)/MAX(H17,'01_Model_Config'!$B$40)))) | J17: =ROUND(IF(F17<'01_Model_Config'!$B$26,D17,MIN('01_Model_Config'!$B$28,MAX('01_Model_Config'!$B$27,MIN(D17+'01_Model_Config'!$B$42,MAX(D17-'01_Model_Config'!$B$42,'01_Model_Config'!$B$24+'01_Model_Config'!$B$25*I17))))),2) | K17: =IF(J17>='01_Model_Config'!$A$16,'01_Model_Config'!$C$16,IF(J17>='01_Model_Config'!$A$17,'01_Model_Config'!$C$17,IF(J17>='01_Model_Config'!$A$18,'01_Model_Config'!$C$18,IF(J17>='01_Model_Config'!$A$19,'01_Model_Config'!$C$19,'01_Model_Config'!$C$20)))) | L17: =IF(J17>='01_Model_Config'!$A$16,'01_Model_Config'!$E$16,IF(J17>='01_Model_Config'!$A$17,'01_Model_Config'!$E$17,IF(J17>='01_Model_Config'!$A$18,'01_Model_Config'!$E$18,IF(J17>='01_Model_Config'!$A$19,'01_Model_Config'!$E$19,'01_Model_Config'!$E$20)))) | M17: =ROUND(STDEV.S('04_Pillar_Calculation'!C17:H17),2) | N17: =ROUND(MAX('04_Pillar_Calculation'!C17:H17)-MIN('04_Pillar_Calculation'!C17:H17),2) | O17: =IF(F17<'01_Model_Config'!$B$26,"MEDIUM",IF(M17>=PERCENTILE.INC($M$5:M16,0.67),"HIGH",IF(M17<=PERCENTILE.INC($M$5:M16,0.33),"LOW","MEDIUM"))) | P17: =IF(F17<'01_Model_Config'!$B$26,"HOLD",IF(D17>=R17,"BUY/ACCUMULATE",IF(D17<=Q17,"REDUCE/SELL","HOLD"))) | Q17: =IF(F17<'01_Model_Config'!$B$26,"",PERCENTILE.INC($D$5:D16,0.15)) | R17: =IF(F17<'01_Model_Config'!$B$26,"",PERCENTILE.INC($D$5:D16,0.85)) | S17: =ROUND(D17,2)
... A28: ='04_Pillar_Calculation'!A28 | B28: ='04_Pillar_Calculation'!B28 | C28: ='02_Market_Inputs'!C28 | D28: ='04_Pillar_Calculation'!O28 | E28: =IF(D28>='01_Model_Config'!$A$16,'01_Model_Config'!$C$16,IF(D28>='01_Model_Config'!$A$17,'01_Model_Config'!$C$17,IF(D28>='01_Model_Config'!$A$18,'01_Model_Config'!$C$18,IF(D28>='01_Model_Config'!$A$19,'01_Model_Config'!$C$19,'01_Model_Config'!$C$20)))) | F28: =ROWS($D$5:D28)-1 | G28: =IF(F28<'01_Model_Config'!$B$26,"",AVERAGE($D$5:D27)) | H28: =IF(F28<'01_Model_Config'!$B$26,"",STDEV.S($D$5:D27)) | I28: =IF(F28<'01_Model_Config'!$B$26,"",MIN('01_Model_Config'!$B$41,MAX(-'01_Model_Config'!$B$41,(D28-G28)/MAX(H28,'01_Model_Config'!$B$40)))) | J28: =ROUND(IF(F28<'01_Model_Config'!$B$26,D28,MIN('01_Model_Config'!$B$28,MAX('01_Model_Config'!$B$27,MIN(D28+'01_Model_Config'!$B$42,MAX(D28-'01_Model_Config'!$B$42,'01_Model_Config'!$B$24+'01_Model_Config'!$B$25*I28))))),2) | K28: =IF(J28>='01_Model_Config'!$A$16,'01_Model_Config'!$C$16,IF(J28>='01_Model_Config'!$A$17,'01_Model_Config'!$C$17,IF(J28>='01_Model_Config'!$A$18,'01_Model_Config'!$C$18,IF(J28>='01_Model_Config'!$A$19,'01_Model_Config'!$C$19,'01_Model_Config'!$C$20)))) | L28: =IF(J28>='01_Model_Config'!$A$16,'01_Model_Config'!$E$16,IF(J28>='01_Model_Config'!$A$17,'01_Model_Config'!$E$17,IF(J28>='01_Model_Config'!$A$18,'01_Model_Config'!$E$18,IF(J28>='01_Model_Config'!$A$19,'01_Model_Config'!$E$19,'01_Model_Config'!$E$20)))) | M28: =ROUND(STDEV.S('04_Pillar_Calculation'!C28:H28),2) | N28: =ROUND(MAX('04_Pillar_Calculation'!C28:H28)-MIN('04_Pillar_Calculation'!C28:H28),2) | O28: =IF(F28<'01_Model_Config'!$B$26,"MEDIUM",IF(M28>=PERCENTILE.INC($M$5:M27,0.67),"HIGH",IF(M28<=PERCENTILE.INC($M$5:M27,0.33),"LOW","MEDIUM"))) | P28: =IF(F28<'01_Model_Config'!$B$26,"HOLD",IF(D28>=R28,"BUY/ACCUMULATE",IF(D28<=Q28,"REDUCE/SELL","HOLD"))) | Q28: =IF(F28<'01_Model_Config'!$B$26,"",PERCENTILE.INC($D$5:D27,0.15)) | R28: =IF(F28<'01_Model_Config'!$B$26,"",PERCENTILE.INC($D$5:D27,0.85)) | S28: =ROUND(D28,2)

Sheet 06_MLR_Regression
A1: MULTIPLE LINEAR REGRESSION — FORECAST & QUALITY LEDGER
A2: Newey-West HAC specification; source forecasts are model outputs, while bonuses and normalized signal scores are formulas
A4: Quarter | B4: As-of Date | C4: Observations | D4: R² | E4: Adjusted R² | F4: Forecast / Day | G4: Quality Bonus | H4: Signal Score
A5: ='02_Market_Inputs'!A5 | B5: ='02_Market_Inputs'!B5 | C5: 750 | D5: 0.2244 | E5: 0.1994 | F5: -0.0005 | G5: =MIN(10,E5*10) | H5: =MIN(100,MAX(0,50+F5*'01_Model_Config'!$B$32))
A6: ='02_Market_Inputs'!A6 | B6: ='02_Market_Inputs'!B6 | C6: 810 | D6: 0.2183 | E6: 0.1933 | F6: 0.0036 | G6: =MIN(10,E6*10) | H6: =MIN(100,MAX(0,50+F6*'01_Model_Config'!$B$32))
A7: ='02_Market_Inputs'!A7 | B7: ='02_Market_Inputs'!B7 | C7: 870 | D7: 0.2323 | E7: 0.2073 | F7: 0.0061 | G7: =MIN(10,E7*10) | H7: =MIN(100,MAX(0,50+F7*'01_Model_Config'!$B$32))
A8: ='02_Market_Inputs'!A8 | B8: ='02_Market_Inputs'!B8 | C8: 930 | D8: 0.231 | E8: 0.206 | F8: 0.0009 | G8: =MIN(10,E8*10) | H8: =MIN(100,MAX(0,50+F8*'01_Model_Config'!$B$32))
A9: ='02_Market_Inputs'!A9 | B9: ='02_Market_Inputs'!B9 | C9: 990 | D9: 0.2196 | E9: 0.1946 | F9: 0.0001 | G9: =MIN(10,E9*10) | H9: =MIN(100,MAX(0,50+F9*'01_Model_Config'!$B$32))
A10: ='02_Market_Inputs'!A10 | B10: ='02_Market_Inputs'!B10 | C10: 1050 | D10: 0.2305 | E10: 0.2055 | F10: -0.0005 | G10: =MIN(10,E10*10) | H10: =MIN(100,MAX(0,50+F10*'01_Model_Config'!$B$32))
A11: ='02_Market_Inputs'!A11 | B11: ='02_Market_Inputs'!B11 | C11: 1110 | D11: 0.1905 | E11: 0.1655 | F11: 0.0032 | G11: =MIN(10,E11*10) | H11: =MIN(100,MAX(0,50+F11*'01_Model_Config'!$B$32))
A12: ='02_Market_Inputs'!A12 | B12: ='02_Market_Inputs'!B12 | C12: 1170 | D12: 0.1832 | E12: 0.1582 | F12: -0.0002 | G12: =MIN(10,E12*10) | H12: =MIN(100,MAX(0,50+F12*'01_Model_Config'!$B$32))
A13: ='02_Market_Inputs'!A13 | B13: ='02_Market_Inputs'!B13 | C13: 1230 | D13: 0.1778 | E13: 0.1528 | F13: 0.0004 | G13: =MIN(10,E13*10) | H13: =MIN(100,MAX(0,50+F13*'01_Model_Config'!$B$32))
A14: ='02_Market_Inputs'!A14 | B14: ='02_Market_Inputs'!B14 | C14: 1290 | D14: 0.1793 | E14: 0.1543 | F14: 0.0002 | G14: =MIN(10,E14*10) | H14: =MIN(100,MAX(0,50+F14*'01_Model_Config'!$B$32))
A15: ='02_Market_Inputs'!A15 | B15: ='02_Market_Inputs'!B15 | C15: 1350 | D15: 0.1824 | E15: 0.1574 | F15: 0.0005 | G15: =MIN(10,E15*10) | H15: =MIN(100,MAX(0,50+F15*'01_Model_Config'!$B$32))
A16: ='02_Market_Inputs'!A16 | B16: ='02_Market_Inputs'!B16 | C16: 1410 | D16: 0.1555 | E16: 0.1305 | F16: 0.0002 | G16: =MIN(10,E16*10) | H16: =MIN(100,MAX(0,50+F16*'01_Model_Config'!$B$32))
... A28: ='02_Market_Inputs'!A28 | B28: ='02_Market_Inputs'!B28 | C28: 2130 | D28: 0.085207048 | E28: 0.060207048 | F28: -0.00023701582 | G28: =MIN(10,E28*10) | H28: =MIN(100,MAX(0,50+F28*'01_Model_Config'!$B$32))

Sheet 07_VAR_Granger
A1: VECTOR AUTOREGRESSION & GRANGER CAUSALITY
A2: P-values are point-in-time model outputs; leader counts and VAR signal normalization are live formulas
A4: Quarter | B4: As-of Date | C4: Optimal Lag | D4: Test 1 p | E4: Test 2 p | F4: Test 3 p | G4: Test 4 p | H4: Test 5 p | I4: Leaders p<5% | J4: VAR T+5 Forecast | K4: VAR Signal Score
A5: ='02_Market_Inputs'!A5 | B5: ='02_Market_Inputs'!B5 | C5: 2 | D5: 0.085 | E5: 0.0885 | F5: 0.2256 | I5: =COUNTIF(D5:H5,"<0.05") | J5: 0.0016 | K5: =MIN(100,MAX(0,50+J5*'01_Model_Config'!$B$33))
A6: ='02_Market_Inputs'!A6 | B6: ='02_Market_Inputs'!B6 | C6: 2 | D6: 0.1707 | E6: 0.1764 | F6: 0.2568 | I6: =COUNTIF(D6:H6,"<0.05") | J6: -0.0007 | K6: =MIN(100,MAX(0,50+J6*'01_Model_Config'!$B$33))
A7: ='02_Market_Inputs'!A7 | B7: ='02_Market_Inputs'!B7 | C7: 2 | D7: 0.1862 | E7: 0.2239 | F7: 0.2569 | I7: =COUNTIF(D7:H7,"<0.05") | J7: 0.0005 | K7: =MIN(100,MAX(0,50+J7*'01_Model_Config'!$B$33))
A8: ='02_Market_Inputs'!A8 | B8: ='02_Market_Inputs'!B8 | C8: 2 | D8: 0.0887 | E8: 0.143 | F8: 0.2181 | I8: =COUNTIF(D8:H8,"<0.05") | J8: -0.0004 | K8: =MIN(100,MAX(0,50+J8*'01_Model_Config'!$B$33))
A9: ='02_Market_Inputs'!A9 | B9: ='02_Market_Inputs'!B9 | C9: 2 | D9: 0.0509 | E9: 0.0853 | F9: 0.1552 | I9: =COUNTIF(D9:H9,"<0.05") | J9: 0.001 | K9: =MIN(100,MAX(0,50+J9*'01_Model_Config'!$B$33))
A10: ='02_Market_Inputs'!A10 | B10: ='02_Market_Inputs'!B10 | C10: 2 | D10: 0.0719 | E10: 0.3944 | F10: 0.6731 | I10: =COUNTIF(D10:H10,"<0.05") | J10: 0.0001 | K10: =MIN(100,MAX(0,50+J10*'01_Model_Config'!$B$33))
A11: ='02_Market_Inputs'!A11 | B11: ='02_Market_Inputs'!B11 | C11: 2 | D11: 0.0182 | E11: 0.2402 | F11: 0.6989 | I11: =COUNTIF(D11:H11,"<0.05") | J11: -0.0006 | K11: =MIN(100,MAX(0,50+J11*'01_Model_Config'!$B$33))
A12: ='02_Market_Inputs'!A12 | B12: ='02_Market_Inputs'!B12 | C12: 2 | D12: 0.0064 | E12: 0.147 | F12: 0.8678 | I12: =COUNTIF(D12:H12,"<0.05") | J12: 0.0004 | K12: =MIN(100,MAX(0,50+J12*'01_Model_Config'!$B$33))
A13: ='02_Market_Inputs'!A13 | B13: ='02_Market_Inputs'!B13 | C13: 2 | D13: 0.0006 | E13: 0.883 | F13: 0.9572 | I13: =COUNTIF(D13:H13,"<0.05") | J13: 0.0002 | K13: =MIN(100,MAX(0,50+J13*'01_Model_Config'!$B$33))
A14: ='02_Market_Inputs'!A14 | B14: ='02_Market_Inputs'!B14 | C14: 2 | D14: 0.0004 | E14: 0.4647 | F14: 0.7383 | I14: =COUNTIF(D14:H14,"<0.05") | J14: -0.0002 | K14: =MIN(100,MAX(0,50+J14*'01_Model_Config'!$B$33))
A15: ='02_Market_Inputs'!A15 | B15: ='02_Market_Inputs'!B15 | C15: 2 | D15: 0.0005 | E15: 0.4777 | F15: 0.6981 | I15: =COUNTIF(D15:H15,"<0.05") | J15: 0.0003 | K15: =MIN(100,MAX(0,50+J15*'01_Model_Config'!$B$33))
A16: ='02_Market_Inputs'!A16 | B16: ='02_Market_Inputs'!B16 | C16: 2 | D16: 0.0002 | E16: 0.4104 | F16: 0.6478 | I16: =COUNTIF(D16:H16,"<0.05") | J16: 0.0002 | K16: =MIN(100,MAX(0,50+J16*'01_Model_Config'!$B$33))
... A22: ='02_Market_Inputs'!A22 | B22: ='02_Market_Inputs'!B22 | C22: 2 | D22: 0 | E22: 0.6438 | F22: 0.7182 | I22: =COUNTIF(D22:H22,"<0.05") | J22: -0.0002 | K22: =MIN(100,MAX(0,50+J22*'01_Model_Config'!$B$33))
A23: ='02_Market_Inputs'!A23 | B23: ='02_Market_Inputs'!B23 | C23: 2 | D23: 0.0027 | E23: 0.029 | F23: 0.7892 | G23: 0.9697 | I23: =COUNTIF(D23:H23,"<0.05") | J23: 0 | K23: =MIN(100,MAX(0,50+J23*'01_Model_Config'!$B$33))
A24: ='02_Market_Inputs'!A24 | B24: ='02_Market_Inputs'!B24 | C24: 2 | D24: 0.0011 | E24: 0.0687 | F24: 0.7216 | G24: 0.9933 | I24: =COUNTIF(D24:H24,"<0.05") | J24: 0.0003 | K24: =MIN(100,MAX(0,50+J24*'01_Model_Config'!$B$33))
A25: ='02_Market_Inputs'!A25 | B25: ='02_Market_Inputs'!B25 | C25: 2 | D25: 0.0033 | E25: 0.0439 | F25: 0.4346 | G25: 0.9382 | I25: =COUNTIF(D25:H25,"<0.05") | J25: 0.0003 | K25: =MIN(100,MAX(0,50+J25*'01_Model_Config'!$B$33))
A26: ='02_Market_Inputs'!A26 | B26: ='02_Market_Inputs'!B26 | C26: 2 | D26: 0.0124 | E26: 0.0291 | F26: 0.3268 | G26: 0.6913 | I26: =COUNTIF(D26:H26,"<0.05") | J26: 0.0004 | K26: =MIN(100,MAX(0,50+J26*'01_Model_Config'!$B$33))
A27: ='02_Market_Inputs'!A27 | B27: ='02_Market_Inputs'!B27 | C27: 2 | D27: 0.0069 | E27: 0.0462 | F27: 0.2816 | G27: 0.7075 | I27: =COUNTIF(D27:H27,"<0.05") | J27: 0.0006 | K27: =MIN(100,MAX(0,50+J27*'01_Model_Config'!$B$33))
A28: ='02_Market_Inputs'!A28 | B28: ='02_Market_Inputs'!B28 | C28: 2 | D28: 0 | E28: 0.0908 | F28: 0.3701 | G28: 0.725 | H28: 0.7961 | I28: =COUNTIF(D28:H28,"<0.05") | J28: 0.00014658262 | K28: =MIN(100,MAX(0,50+J28*'01_Model_Config'!$B$33))

Sheet 08_ML_Validation
A1: XGBOOST WALK-FORWARD VALIDATION
A2: Eight-fold expanding walk-forward metrics and formula-normalized quality/directional scores
A4: Quarter | B4: As-of Date | C4: Model | D4: WFV Folds | E4: Feature Count | F4: Mean Accuracy | G4: Mean F1 | H4: Predicted Class | I4: Prediction | J4: Confidence | K4: Quality Score | L4: Signal Score
A5: ='02_Market_Inputs'!A5 | B5: ='02_Market_Inputs'!B5 | C5: xgboost | D5: 8 | E5: 72 | F5: 0.5263 | G5: 0.52 | H5: 1 | I5: UP | J5: 0.987 | K5: =MIN(100,MAX(0,(F5+G5)/2*100)) | L5: =MIN(100,MAX(0,50+IF(H5=1,1,IF(H5=-1,-1,0))*30*MAX(0,(J5-1/3)/(1-1/3))))
A6: ='02_Market_Inputs'!A6 | B6: ='02_Market_Inputs'!B6 | C6: xgboost | D6: 8 | E6: 72 | F6: 0.5966 | G6: 0.5661 | H6: -1 | I6: DOWN | J6: 0.8131 | K6: =MIN(100,MAX(0,(F6+G6)/2*100)) | L6: =MIN(100,MAX(0,50+IF(H6=1,1,IF(H6=-1,-1,0))*30*MAX(0,(J6-1/3)/(1-1/3))))
A7: ='02_Market_Inputs'!A7 | B7: ='02_Market_Inputs'!B7 | C7: xgboost | D7: 8 | E7: 72 | F7: 0.524 | G7: 0.5123 | H7: -1 | I7: DOWN | J7: 0.6847 | K7: =MIN(100,MAX(0,(F7+G7)/2*100)) | L7: =MIN(100,MAX(0,50+IF(H7=1,1,IF(H7=-1,-1,0))*30*MAX(0,(J7-1/3)/(1-1/3))))
A8: ='02_Market_Inputs'!A8 | B8: ='02_Market_Inputs'!B8 | C8: xgboost | D8: 8 | E8: 72 | F8: 0.5647 | G8: 0.5278 | H8: -1 | I8: DOWN | J8: 0.4484 | K8: =MIN(100,MAX(0,(F8+G8)/2*100)) | L8: =MIN(100,MAX(0,50+IF(H8=1,1,IF(H8=-1,-1,0))*30*MAX(0,(J8-1/3)/(1-1/3))))
A9: ='02_Market_Inputs'!A9 | B9: ='02_Market_Inputs'!B9 | C9: xgboost | D9: 8 | E9: 72 | F9: 0.5341 | G9: 0.4932 | H9: 1 | I9: UP | J9: 0.82 | K9: =MIN(100,MAX(0,(F9+G9)/2*100)) | L9: =MIN(100,MAX(0,50+IF(H9=1,1,IF(H9=-1,-1,0))*30*MAX(0,(J9-1/3)/(1-1/3))))
A10: ='02_Market_Inputs'!A10 | B10: ='02_Market_Inputs'!B10 | C10: xgboost | D10: 8 | E10: 72 | F10: 0.4444 | G10: 0.4059 | H10: -1 | I10: DOWN | J10: 0.5671 | K10: =MIN(100,MAX(0,(F10+G10)/2*100)) | L10: =MIN(100,MAX(0,50+IF(H10=1,1,IF(H10=-1,-1,0))*30*MAX(0,(J10-1/3)/(1-1/3))))
A11: ='02_Market_Inputs'!A11 | B11: ='02_Market_Inputs'!B11 | C11: xgboost | D11: 8 | E11: 72 | F11: 0.4219 | G11: 0.3642 | H11: 1 | I11: UP | J11: 0.6867 | K11: =MIN(100,MAX(0,(F11+G11)/2*100)) | L11: =MIN(100,MAX(0,50+IF(H11=1,1,IF(H11=-1,-1,0))*30*MAX(0,(J11-1/3)/(1-1/3))))
A12: ='02_Market_Inputs'!A12 | B12: ='02_Market_Inputs'!B12 | C12: xgboost | D12: 8 | E12: 72 | F12: 0.4186 | G12: 0.3801 | H12: -1 | I12: DOWN | J12: 0.9052 | K12: =MIN(100,MAX(0,(F12+G12)/2*100)) | L12: =MIN(100,MAX(0,50+IF(H12=1,1,IF(H12=-1,-1,0))*30*MAX(0,(J12-1/3)/(1-1/3))))
A13: ='02_Market_Inputs'!A13 | B13: ='02_Market_Inputs'!B13 | C13: xgboost | D13: 8 | E13: 72 | F13: 0.4016 | G13: 0.3292 | H13: 1 | I13: UP | J13: 0.5865 | K13: =MIN(100,MAX(0,(F13+G13)/2*100)) | L13: =MIN(100,MAX(0,50+IF(H13=1,1,IF(H13=-1,-1,0))*30*MAX(0,(J13-1/3)/(1-1/3))))
A14: ='02_Market_Inputs'!A14 | B14: ='02_Market_Inputs'!B14 | C14: xgboost | D14: 8 | E14: 72 | F14: 0.415 | G14: 0.3219 | H14: 1 | I14: UP | J14: 0.6443 | K14: =MIN(100,MAX(0,(F14+G14)/2*100)) | L14: =MIN(100,MAX(0,50+IF(H14=1,1,IF(H14=-1,-1,0))*30*MAX(0,(J14-1/3)/(1-1/3))))
A15: ='02_Market_Inputs'!A15 | B15: ='02_Market_Inputs'!B15 | C15: xgboost | D15: 8 | E15: 72 | F15: 0.4293 | G15: 0.3502 | H15: 1 | I15: UP | J15: 0.5075 | K15: =MIN(100,MAX(0,(F15+G15)/2*100)) | L15: =MIN(100,MAX(0,50+IF(H15=1,1,IF(H15=-1,-1,0))*30*MAX(0,(J15-1/3)/(1-1/3))))
A16: ='02_Market_Inputs'!A16 | B16: ='02_Market_Inputs'!B16 | C16: xgboost | D16: 8 | E16: 76 | F16: 0.4145 | G16: 0.3461 | H16: -1 | I16: DOWN | J16: 0.8353 | K16: =MIN(100,MAX(0,(F16+G16)/2*100)) | L16: =MIN(100,MAX(0,50+IF(H16=1,1,IF(H16=-1,-1,0))*30*MAX(0,(J16-1/3)/(1-1/3))))
... A28: ='02_Market_Inputs'!A28 | B28: ='02_Market_Inputs'!B28 | C28: xgboost | D28: 8 | E28: 136 | F28: 0.4846 | G28: 0.4326 | H28: -1 | I28: DOWN | J28: 0.6265 | K28: =MIN(100,MAX(0,(F28+G28)/2*100)) | L28: =MIN(100,MAX(0,50+IF(H28=1,1,IF(H28=-1,-1,0))*30*MAX(0,(J28-1/3)/(1-1/3))))

Sheet 09_Feature_Importance
A1: XGBOOST FEATURE GAIN IMPORTANCE — LATEST QUARTER
A2: Gain values are model outputs; rank and cumulative contribution are formula-driven
A5: Formula Rank | B5: Feature | C5: Category | D5: Gain | E5: Cumulative Gain by Rank | F5: Interpretation
A6: =RANK.EQ(D6,$D$6:$D$20,0) | B6: m2_yoy_pct | C6: Technical / Market | D6: 0.01707468 | E6: =SUMIF($A$6:$A$20,"<="&A6,$D$6:$D$20) | F6: XGBoost out-of-sample gain contribution
A7: =RANK.EQ(D7,$D$6:$D$20,0) | B7: bb_lower | C7: Technical / Market | D7: 0.014571746 | E7: =SUMIF($A$6:$A$20,"<="&A7,$D$6:$D$20) | F7: XGBoost out-of-sample gain contribution
A8: =RANK.EQ(D8,$D$6:$D$20,0) | B8: ema_20 | C8: Technical / Market | D8: 0.014216051 | E8: =SUMIF($A$6:$A$20,"<="&A8,$D$6:$D$20) | F8: XGBoost out-of-sample gain contribution
A9: =RANK.EQ(D9,$D$6:$D$20,0) | B9: bb_mid | C9: Technical / Market | D9: 0.013340008 | E9: =SUMIF($A$6:$A$20,"<="&A9,$D$6:$D$20) | F9: XGBoost out-of-sample gain contribution
A10: =RANK.EQ(D10,$D$6:$D$20,0) | B10: us10y_30d_change | C10: Global / Rates | D10: 0.013147972 | E10: =SUMIF($A$6:$A$20,"<="&A10,$D$6:$D$20) | F10: XGBoost out-of-sample gain contribution
A11: =RANK.EQ(D11,$D$6:$D$20,0) | B11: us10y_zscore_1y | C11: Global / Rates | D11: 0.01264037 | E11: =SUMIF($A$6:$A$20,"<="&A11,$D$6:$D$20) | F11: XGBoost out-of-sample gain contribution
A12: =RANK.EQ(D12,$D$6:$D$20,0) | B12: oil_n_shock_days_ytd | C12: Technical / Market | D12: 0.012422486 | E12: =SUMIF($A$6:$A$20,"<="&A12,$D$6:$D$20) | F12: XGBoost out-of-sample gain contribution
A13: =RANK.EQ(D13,$D$6:$D$20,0) | B13: macd_line | C13: Technical / Market | D13: 0.012322888 | E13: =SUMIF($A$6:$A$20,"<="&A13,$D$6:$D$20) | F13: XGBoost out-of-sample gain contribution
A14: =RANK.EQ(D14,$D$6:$D$20,0) | B14: oil_max_weekly_change_ytd | C14: Technical / Market | D14: 0.012129197 | E14: =SUMIF($A$6:$A$20,"<="&A14,$D$6:$D$20) | F14: XGBoost out-of-sample gain contribution
A15: =RANK.EQ(D15,$D$6:$D$20,0) | B15: valuation_composite_score | C15: Technical / Market | D15: 0.010881403 | E15: =SUMIF($A$6:$A$20,"<="&A15,$D$6:$D$20) | F15: XGBoost out-of-sample gain contribution
A16: =RANK.EQ(D16,$D$6:$D$20,0) | B16: headline_pe | C16: Technical / Market | D16: 0.010805807 | E16: =SUMIF($A$6:$A$20,"<="&A16,$D$6:$D$20) | F16: XGBoost out-of-sample gain contribution
A17: =RANK.EQ(D17,$D$6:$D$20,0) | B17: dxy_zscore_60d | C17: Global / Rates | D17: 0.010690039 | E17: =SUMIF($A$6:$A$20,"<="&A17,$D$6:$D$20) | F17: XGBoost out-of-sample gain contribution
... A20: =RANK.EQ(D20,$D$6:$D$20,0) | B20: macd_signal | C20: Technical / Market | D20: 0.010483006 | E20: =SUMIF($A$6:$A$20,"<="&A20,$D$6:$D$20) | F20: XGBoost out-of-sample gain contribution

Sheet 10_Backtest_Efficacy
A1: ASSET-ALLOCATION BACKTEST & SIGNAL EFFICACY
A2: As-of close is strictly t−1; outcome close is separate. Dashboard-compatible t+1 returns are explicitly labelled, never used in scoring
A4: Quarter | B4: As-of Close (t−1) | C4: Quarter-End Outcome Close | D4: Strict Quarter Return | E4: Dashboard Fwd Return (t+1) | F4: Calibrated Action | G4: Equity Weight | H4: Cash Weight | I4: Cash Quarterly Yield | J4: Strategy Return | K4: Strategy NAV | L4: Benchmark NAV | M4: Peak NAV | N4: Drawdown | O4: Direction Hit | P4: Raw Score Rank | Q4: Strict Return Rank | R4: Benchmark Peak | S4: Benchmark Drawdown
A5: ='02_Market_Inputs'!A5 | B5: ='02_Market_Inputs'!C5 | C5: ='02_Market_Inputs'!D5 | D5: =IF(OR(B5=0,C5=0),"",C5/B5-1) | E5: =IF(OR(C5=0,C6=0),0,C6/C5-1) | F5: ='05_Composite_Calibration'!K5 | G5: =IF(F5='01_Model_Config'!$C$16,'01_Model_Config'!$F$16,IF(F5='01_Model_Config'!$C$17,'01_Model_Config'!$F$17,IF(F5='01_Model_Config'!$C$18,'01_Model_Config'!$F$18,IF(F5='01_Model_Config'!$C$19,'01_Model_Config'!$F$19,'01_Model_Config'!$F$20)))) | H5: =1-G5 | I5: =(1+'02_Market_Inputs'!E5/100)^0.25-1 | J5: =G5*E5+H5*I5 | K5: ='01_Model_Config'!$B$35*(1+J5) | L5: ='01_Model_Config'!$B$35*(1+E5) | M5: =MAX($K$5:K5) | N5: =(K5-M5)/M5 | O5: =IF(OR(AND(F5="BUY",E5>0),AND(F5="ACCUMULATE",E5>0),AND(F5="HOLD",ABS(E5)<0.05),AND(F5="REDUCE",E5<0),AND(F5="SELL",E5<0)),1,0) | P5: =IF(ROW()>=28,"",RANK.EQ('05_Composite_Calibration'!S5,'05_Composite_Calibration'!$S$5:$S$27,1)+(COUNTIF('05_Composite_Calibration'!$S$5:$S$27,'05_Composite_Calibration'!S5)-1)/2) | Q5: =IF(ROW()>=28,"",RANK.EQ(D5,$D$5:$D$27,1)+(COUNTIF($D$5:$D$27,D5)-1)/2) | R5: =MAX($L$5:L5) | S5: =(L5-R5)/R5
A6: ='02_Market_Inputs'!A6 | B6: ='02_Market_Inputs'!C6 | C6: ='02_Market_Inputs'!D6 | D6: =IF(OR(B6=0,C6=0),"",C6/B6-1) | E6: =IF(OR(C6=0,C7=0),0,C7/C6-1) | F6: ='05_Composite_Calibration'!K6 | G6: =IF(F6='01_Model_Config'!$C$16,'01_Model_Config'!$F$16,IF(F6='01_Model_Config'!$C$17,'01_Model_Config'!$F$17,IF(F6='01_Model_Config'!$C$18,'01_Model_Config'!$F$18,IF(F6='01_Model_Config'!$C$19,'01_Model_Config'!$F$19,'01_Model_Config'!$F$20)))) | H6: =1-G6 | I6: =(1+'02_Market_Inputs'!E6/100)^0.25-1 | J6: =G6*E6+H6*I6 | K6: =K5*(1+J6) | L6: =L5*(1+E6) | M6: =MAX($K$5:K6) | N6: =(K6-M6)/M6 | O6: =IF(OR(AND(F6="BUY",E6>0),AND(F6="ACCUMULATE",E6>0),AND(F6="HOLD",ABS(E6)<0.05),AND(F6="REDUCE",E6<0),AND(F6="SELL",E6<0)),1,0) | P6: =IF(ROW()>=28,"",RANK.EQ('05_Composite_Calibration'!S6,'05_Composite_Calibration'!$S$5:$S$27,1)+(COUNTIF('05_Composite_Calibration'!$S$5:$S$27,'05_Composite_Calibration'!S6)-1)/2) | Q6: =IF(ROW()>=28,"",RANK.EQ(D6,$D$5:$D$27,1)+(COUNTIF($D$5:$D$27,D6)-1)/2) | R6: =MAX($L$5:L6) | S6: =(L6-R6)/R6
A7: ='02_Market_Inputs'!A7 | B7: ='02_Market_Inputs'!C7 | C7: ='02_Market_Inputs'!D7 | D7: =IF(OR(B7=0,C7=0),"",C7/B7-1) | E7: =IF(OR(C7=0,C8=0),0,C8/C7-1) | F7: ='05_Composite_Calibration'!K7 | G7: =IF(F7='01_Model_Config'!$C$16,'01_Model_Config'!$F$16,IF(F7='01_Model_Config'!$C$17,'01_Model_Config'!$F$17,IF(F7='01_Model_Config'!$C$18,'01_Model_Config'!$F$18,IF(F7='01_Model_Config'!$C$19,'01_Model_Config'!$F$19,'01_Model_Config'!$F$20)))) | H7: =1-G7 | I7: =(1+'02_Market_Inputs'!E7/100)^0.25-1 | J7: =G7*E7+H7*I7 | K7: =K6*(1+J7) | L7: =L6*(1+E7) | M7: =MAX($K$5:K7) | N7: =(K7-M7)/M7 | O7: =IF(OR(AND(F7="BUY",E7>0),AND(F7="ACCUMULATE",E7>0),AND(F7="HOLD",ABS(E7)<0.05),AND(F7="REDUCE",E7<0),AND(F7="SELL",E7<0)),1,0) | P7: =IF(ROW()>=28,"",RANK.EQ('05_Composite_Calibration'!S7,'05_Composite_Calibration'!$S$5:$S$27,1)+(COUNTIF('05_Composite_Calibration'!$S$5:$S$27,'05_Composite_Calibration'!S7)-1)/2) | Q7: =IF(ROW()>=28,"",RANK.EQ(D7,$D$5:$D$27,1)+(COUNTIF($D$5:$D$27,D7)-1)/2) | R7: =MAX($L$5:L7) | S7: =(L7-R7)/R7
A8: ='02_Market_Inputs'!A8 | B8: ='02_Market_Inputs'!C8 | C8: ='02_Market_Inputs'!D8 | D8: =IF(OR(B8=0,C8=0),"",C8/B8-1) | E8: =IF(OR(C8=0,C9=0),0,C9/C8-1) | F8: ='05_Composite_Calibration'!K8 | G8: =IF(F8='01_Model_Config'!$C$16,'01_Model_Config'!$F$16,IF(F8='01_Model_Config'!$C$17,'01_Model_Config'!$F$17,IF(F8='01_Model_Config'!$C$18,'01_Model_Config'!$F$18,IF(F8='01_Model_Config'!$C$19,'01_Model_Config'!$F$19,'01_Model_Config'!$F$20)))) | H8: =1-G8 | I8: =(1+'02_Market_Inputs'!E8/100)^0.25-1 | J8: =G8*E8+H8*I8 | K8: =K7*(1+J8) | L8: =L7*(1+E8) | M8: =MAX($K$5:K8) | N8: =(K8-M8)/M8 | O8: =IF(OR(AND(F8="BUY",E8>0),AND(F8="ACCUMULATE",E8>0),AND(F8="HOLD",ABS(E8)<0.05),AND(F8="REDUCE",E8<0),AND(F8="SELL",E8<0)),1,0) | P8: =IF(ROW()>=28,"",RANK.EQ('05_Composite_Calibration'!S8,'05_Composite_Calibration'!$S$5:$S$27,1)+(COUNTIF('05_Composite_Calibration'!$S$5:$S$27,'05_Composite_Calibration'!S8)-1)/2) | Q8: =IF(ROW()>=28,"",RANK.EQ(D8,$D$5:$D$27,1)+(COUNTIF($D$5:$D$27,D8)-1)/2) | R8: =MAX($L$5:L8) | S8: =(L8-R8)/R8
A9: ='02_Market_Inputs'!A9 | B9: ='02_Market_Inputs'!C9 | C9: ='02_Market_Inputs'!D9 | D9: =IF(OR(B9=0,C9=0),"",C9/B9-1) | E9: =IF(OR(C9=0,C10=0),0,C10/C9-1) | F9: ='05_Composite_Calibration'!K9 | G9: =IF(F9='01_Model_Config'!$C$16,'01_Model_Config'!$F$16,IF(F9='01_Model_Config'!$C$17,'01_Model_Config'!$F$17,IF(F9='01_Model_Config'!$C$18,'01_Model_Config'!$F$18,IF(F9='01_Model_Config'!$C$19,'01_Model_Config'!$F$19,'01_Model_Config'!$F$20)))) | H9: =1-G9 | I9: =(1+'02_Market_Inputs'!E9/100)^0.25-1 | J9: =G9*E9+H9*I9 | K9: =K8*(1+J9) | L9: =L8*(1+E9) | M9: =MAX($K$5:K9) | N9: =(K9-M9)/M9 | O9: =IF(OR(AND(F9="BUY",E9>0),AND(F9="ACCUMULATE",E9>0),AND(F9="HOLD",ABS(E9)<0.05),AND(F9="REDUCE",E9<0),AND(F9="SELL",E9<0)),1,0) | P9: =IF(ROW()>=28,"",RANK.EQ('05_Composite_Calibration'!S9,'05_Composite_Calibration'!$S$5:$S$27,1)+(COUNTIF('05_Composite_Calibration'!$S$5:$S$27,'05_Composite_Calibration'!S9)-1)/2) | Q9: =IF(ROW()>=28,"",RANK.EQ(D9,$D$5:$D$27,1)+(COUNTIF($D$5:$D$27,D9)-1)/2) | R9: =MAX($L$5:L9) | S9: =(L9-R9)/R9
A10: ='02_Market_Inputs'!A10 | B10: ='02_Market_Inputs'!C10 | C10: ='02_Market_Inputs'!D10 | D10: =IF(OR(B10=0,C10=0),"",C10/B10-1) | E10: =IF(OR(C10=0,C11=0),0,C11/C10-1) | F10: ='05_Composite_Calibration'!K10 | G10: =IF(F10='01_Model_Config'!$C$16,'01_Model_Config'!$F$16,IF(F10='01_Model_Config'!$C$17,'01_Model_Config'!$F$17,IF(F10='01_Model_Config'!$C$18,'01_Model_Config'!$F$18,IF(F10='01_Model_Config'!$C$19,'01_Model_Config'!$F$19,'01_Model_Config'!$F$20)))) | H10: =1-G10 | I10: =(1+'02_Market_Inputs'!E10/100)^0.25-1 | J10: =G10*E10+H10*I10 | K10: =K9*(1+J10) | L10: =L9*(1+E10) | M10: =MAX($K$5:K10) | N10: =(K10-M10)/M10 | O10: =IF(OR(AND(F10="BUY",E10>0),AND(F10="ACCUMULATE",E10>0),AND(F10="HOLD",ABS(E10)<0.05),AND(F10="REDUCE",E10<0),AND(F10="SELL",E10<0)),1,0) | P10: =IF(ROW()>=28,"",RANK.EQ('05_Composite_Calibration'!S10,'05_Composite_Calibration'!$S$5:$S$27,1)+(COUNTIF('05_Composite_Calibration'!$S$5:$S$27,'05_Composite_Calibration'!S10)-1)/2) | Q10: =IF(ROW()>=28,"",RANK.EQ(D10,$D$5:$D$27,1)+(COUNTIF($D$5:$D$27,D10)-1)/2) | R10: =MAX($L$5:L10) | S10: =(L10-R10)/R10
A11: ='02_Market_Inputs'!A11 | B11: ='02_Market_Inputs'!C11 | C11: ='02_Market_Inputs'!D11 | D11: =IF(OR(B11=0,C11=0),"",C11/B11-1) | E11: =IF(OR(C11=0,C12=0),0,C12/C11-1) | F11: ='05_Composite_Calibration'!K11 | G11: =IF(F11='01_Model_Config'!$C$16,'01_Model_Config'!$F$16,IF(F11='01_Model_Config'!$C$17,'01_Model_Config'!$F$17,IF(F11='01_Model_Config'!$C$18,'01_Model_Config'!$F$18,IF(F11='01_Model_Config'!$C$19,'01_Model_Config'!$F$19,'01_Model_Config'!$F$20)))) | H11: =1-G11 | I11: =(1+'02_Market_Inputs'!E11/100)^0.25-1 | J11: =G11*E11+H11*I11 | K11: =K10*(1+J11) | L11: =L10*(1+E11) | M11: =MAX($K$5:K11) | N11: =(K11-M11)/M11 | O11: =IF(OR(AND(F11="BUY",E11>0),AND(F11="ACCUMULATE",E11>0),AND(F11="HOLD",ABS(E11)<0.05),AND(F11="REDUCE",E11<0),AND(F11="SELL",E11<0)),1,0) | P11: =IF(ROW()>=28,"",RANK.EQ('05_Composite_Calibration'!S11,'05_Composite_Calibration'!$S$5:$S$27,1)+(COUNTIF('05_Composite_Calibration'!$S$5:$S$27,'05_Composite_Calibration'!S11)-1)/2) | Q11: =IF(ROW()>=28,"",RANK.EQ(D11,$D$5:$D$27,1)+(COUNTIF($D$5:$D$27,D11)-1)/2) | R11: =MAX($L$5:L11) | S11: =(L11-R11)/R11
A12: ='02_Market_Inputs'!A12 | B12: ='02_Market_Inputs'!C12 | C12: ='02_Market_Inputs'!D12 | D12: =IF(OR(B12=0,C12=0),"",C12/B12-1) | E12: =IF(OR(C12=0,C13=0),0,C13/C12-1) | F12: ='05_Composite_Calibration'!K12 | G12: =IF(F12='01_Model_Config'!$C$16,'01_Model_Config'!$F$16,IF(F12='01_Model_Config'!$C$17,'01_Model_Config'!$F$17,IF(F12='01_Model_Config'!$C$18,'01_Model_Config'!$F$18,IF(F12='01_Model_Config'!$C$19,'01_Model_Config'!$F$19,'01_Model_Config'!$F$20)))) | H12: =1-G12 | I12: =(1+'02_Market_Inputs'!E12/100)^0.25-1 | J12: =G12*E12+H12*I12 | K12: =K11*(1+J12) | L12: =L11*(1+E12) | M12: =MAX($K$5:K12) | N12: =(K12-M12)/M12 | O12: =IF(OR(AND(F12="BUY",E12>0),AND(F12="ACCUMULATE",E12>0),AND(F12="HOLD",ABS(E12)<0.05),AND(F12="REDUCE",E12<0),AND(F12="SELL",E12<0)),1,0) | P12: =IF(ROW()>=28,"",RANK.EQ('05_Composite_Calibration'!S12,'05_Composite_Calibration'!$S$5:$S$27,1)+(COUNTIF('05_Composite_Calibration'!$S$5:$S$27,'05_Composite_Calibration'!S12)-1)/2) | Q12: =IF(ROW()>=28,"",RANK.EQ(D12,$D$5:$D$27,1)+(COUNTIF($D$5:$D$27,D12)-1)/2) | R12: =MAX($L$5:L12) | S12: =(L12-R12)/R12
A13: ='02_Market_Inputs'!A13 | B13: ='02_Market_Inputs'!C13 | C13: ='02_Market_Inputs'!D13 | D13: =IF(OR(B13=0,C13=0),"",C13/B13-1) | E13: =IF(OR(C13=0,C14=0),0,C14/C13-1) | F13: ='05_Composite_Calibration'!K13 | G13: =IF(F13='01_Model_Config'!$C$16,'01_Model_Config'!$F$16,IF(F13='01_Model_Config'!$C$17,'01_Model_Config'!$F$17,IF(F13='01_Model_Config'!$C$18,'01_Model_Config'!$F$18,IF(F13='01_Model_Config'!$C$19,'01_Model_Config'!$F$19,'01_Model_Config'!$F$20)))) | H13: =1-G13 | I13: =(1+'02_Market_Inputs'!E13/100)^0.25-1 | J13: =G13*E13+H13*I13 | K13: =K12*(1+J13) | L13: =L12*(1+E13) | M13: =MAX($K$5:K13) | N13: =(K13-M13)/M13 | O13: =IF(OR(AND(F13="BUY",E13>0),AND(F13="ACCUMULATE",E13>0),AND(F13="HOLD",ABS(E13)<0.05),AND(F13="REDUCE",E13<0),AND(F13="SELL",E13<0)),1,0) | P13: =IF(ROW()>=28,"",RANK.EQ('05_Composite_Calibration'!S13,'05_Composite_Calibration'!$S$5:$S$27,1)+(COUNTIF('05_Composite_Calibration'!$S$5:$S$27,'05_Composite_Calibration'!S13)-1)/2) | Q13: =IF(ROW()>=28,"",RANK.EQ(D13,$D$5:$D$27,1)+(COUNTIF($D$5:$D$27,D13)-1)/2) | R13: =MAX($L$5:L13) | S13: =(L13-R13)/R13
A14: ='02_Market_Inputs'!A14 | B14: ='02_Market_Inputs'!C14 | C14: ='02_Market_Inputs'!D14 | D14: =IF(OR(B14=0,C14=0),"",C14/B14-1) | E14: =IF(OR(C14=0,C15=0),0,C15/C14-1) | F14: ='05_Composite_Calibration'!K14 | G14: =IF(F14='01_Model_Config'!$C$16,'01_Model_Config'!$F$16,IF(F14='01_Model_Config'!$C$17,'01_Model_Config'!$F$17,IF(F14='01_Model_Config'!$C$18,'01_Model_Config'!$F$18,IF(F14='01_Model_Config'!$C$19,'01_Model_Config'!$F$19,'01_Model_Config'!$F$20)))) | H14: =1-G14 | I14: =(1+'02_Market_Inputs'!E14/100)^0.25-1 | J14: =G14*E14+H14*I14 | K14: =K13*(1+J14) | L14: =L13*(1+E14) | M14: =MAX($K$5:K14) | N14: =(K14-M14)/M14 | O14: =IF(OR(AND(F14="BUY",E14>0),AND(F14="ACCUMULATE",E14>0),AND(F14="HOLD",ABS(E14)<0.05),AND(F14="REDUCE",E14<0),AND(F14="SELL",E14<0)),1,0) | P14: =IF(ROW()>=28,"",RANK.EQ('05_Composite_Calibration'!S14,'05_Composite_Calibration'!$S$5:$S$27,1)+(COUNTIF('05_Composite_Calibration'!$S$5:$S$27,'05_Composite_Calibration'!S14)-1)/2) | Q14: =IF(ROW()>=28,"",RANK.EQ(D14,$D$5:$D$27,1)+(COUNTIF($D$5:$D$27,D14)-1)/2) | R14: =MAX($L$5:L14) | S14: =(L14-R14)/R14
A15: ='02_Market_Inputs'!A15 | B15: ='02_Market_Inputs'!C15 | C15: ='02_Market_Inputs'!D15 | D15: =IF(OR(B15=0,C15=0),"",C15/B15-1) | E15: =IF(OR(C15=0,C16=0),0,C16/C15-1) | F15: ='05_Composite_Calibration'!K15 | G15: =IF(F15='01_Model_Config'!$C$16,'01_Model_Config'!$F$16,IF(F15='01_Model_Config'!$C$17,'01_Model_Config'!$F$17,IF(F15='01_Model_Config'!$C$18,'01_Model_Config'!$F$18,IF(F15='01_Model_Config'!$C$19,'01_Model_Config'!$F$19,'01_Model_Config'!$F$20)))) | H15: =1-G15 | I15: =(1+'02_Market_Inputs'!E15/100)^0.25-1 | J15: =G15*E15+H15*I15 | K15: =K14*(1+J15) | L15: =L14*(1+E15) | M15: =MAX($K$5:K15) | N15: =(K15-M15)/M15 | O15: =IF(OR(AND(F15="BUY",E15>0),AND(F15="ACCUMULATE",E15>0),AND(F15="HOLD",ABS(E15)<0.05),AND(F15="REDUCE",E15<0),AND(F15="SELL",E15<0)),1,0) | P15: =IF(ROW()>=28,"",RANK.EQ('05_Composite_Calibration'!S15,'05_Composite_Calibration'!$S$5:$S$27,1)+(COUNTIF('05_Composite_Calibration'!$S$5:$S$27,'05_Composite_Calibration'!S15)-1)/2) | Q15: =IF(ROW()>=28,"",RANK.EQ(D15,$D$5:$D$27,1)+(COUNTIF($D$5:$D$27,D15)-1)/2) | R15: =MAX($L$5:L15) | S15: =(L15-R15)/R15
A16: ='02_Market_Inputs'!A16 | B16: ='02_Market_Inputs'!C16 | C16: ='02_Market_Inputs'!D16 | D16: =IF(OR(B16=0,C16=0),"",C16/B16-1) | E16: =IF(OR(C16=0,C17=0),0,C17/C16-1) | F16: ='05_Composite_Calibration'!K16 | G16: =IF(F16='01_Model_Config'!$C$16,'01_Model_Config'!$F$16,IF(F16='01_Model_Config'!$C$17,'01_Model_Config'!$F$17,IF(F16='01_Model_Config'!$C$18,'01_Model_Config'!$F$18,IF(F16='01_Model_Config'!$C$19,'01_Model_Config'!$F$19,'01_Model_Config'!$F$20)))) | H16: =1-G16 | I16: =(1+'02_Market_Inputs'!E16/100)^0.25-1 | J16: =G16*E16+H16*I16 | K16: =K15*(1+J16) | L16: =L15*(1+E16) | M16: =MAX($K$5:K16) | N16: =(K16-M16)/M16 | O16: =IF(OR(AND(F16="BUY",E16>0),AND(F16="ACCUMULATE",E16>0),AND(F16="HOLD",ABS(E16)<0.05),AND(F16="REDUCE",E16<0),AND(F16="SELL",E16<0)),1,0) | P16: =IF(ROW()>=28,"",RANK.EQ('05_Composite_Calibration'!S16,'05_Composite_Calibration'!$S$5:$S$27,1)+(COUNTIF('05_Composite_Calibration'!$S$5:$S$27,'05_Composite_Calibration'!S16)-1)/2) | Q16: =IF(ROW()>=28,"",RANK.EQ(D16,$D$5:$D$27,1)+(COUNTIF($D$5:$D$27,D16)-1)/2) | R16: =MAX($L$5:L16) | S16: =(L16-R16)/R16
A17: ='02_Market_Inputs'!A17 | B17: ='02_Market_Inputs'!C17 | C17: ='02_Market_Inputs'!D17 | D17: =IF(OR(B17=0,C17=0),"",C17/B17-1) | E17: =IF(OR(C17=0,C18=0),0,C18/C17-1) | F17: ='05_Composite_Calibration'!K17 | G17: =IF(F17='01_Model_Config'!$C$16,'01_Model_Config'!$F$16,IF(F17='01_Model_Config'!$C$17,'01_Model_Config'!$F$17,IF(F17='01_Model_Config'!$C$18,'01_Model_Config'!$F$18,IF(F17='01_Model_Config'!$C$19,'01_Model_Config'!$F$19,'01_Model_Config'!$F$20)))) | H17: =1-G17 | I17: =(1+'02_Market_Inputs'!E17/100)^0.25-1 | J17: =G17*E17+H17*I17 | K17: =K16*(1+J17) | L17: =L16*(1+E17) | M17: =MAX($K$5:K17) | N17: =(K17-M17)/M17 | O17: =IF(OR(AND(F17="BUY",E17>0),AND(F17="ACCUMULATE",E17>0),AND(F17="HOLD",ABS(E17)<0.05),AND(F17="REDUCE",E17<0),AND(F17="SELL",E17<0)),1,0) | P17: =IF(ROW()>=28,"",RANK.EQ('05_Composite_Calibration'!S17,'05_Composite_Calibration'!$S$5:$S$27,1)+(COUNTIF('05_Composite_Calibration'!$S$5:$S$27,'05_Composite_Calibration'!S17)-1)/2) | Q17: =IF(ROW()>=28,"",RANK.EQ(D17,$D$5:$D$27,1)+(COUNTIF($D$5:$D$27,D17)-1)/2) | R17: =MAX($L$5:L17) | S17: =(L17-R17)/R17
... A27: ='02_Market_Inputs'!A27 | B27: ='02_Market_Inputs'!C27 | C27: ='02_Market_Inputs'!D27 | D27: =IF(OR(B27=0,C27=0),"",C27/B27-1) | E27: =IF(OR(C27=0,C28=0),0,C28/C27-1) | F27: ='05_Composite_Calibration'!K27 | G27: =IF(F27='01_Model_Config'!$C$16,'01_Model_Config'!$F$16,IF(F27='01_Model_Config'!$C$17,'01_Model_Config'!$F$17,IF(F27='01_Model_Config'!$C$18,'01_Model_Config'!$F$18,IF(F27='01_Model_Config'!$C$19,'01_Model_Config'!$F$19,'01_Model_Config'!$F$20)))) | H27: =1-G27 | I27: =(1+'02_Market_Inputs'!E27/100)^0.25-1 | J27: =G27*E27+H27*I27 | K27: =K26*(1+J27) | L27: =L26*(1+E27) | M27: =MAX($K$5:K27) | N27: =(K27-M27)/M27 | O27: =IF(OR(AND(F27="BUY",E27>0),AND(F27="ACCUMULATE",E27>0),AND(F27="HOLD",ABS(E27)<0.05),AND(F27="REDUCE",E27<0),AND(F27="SELL",E27<0)),1,0) | P27: =IF(ROW()>=28,"",RANK.EQ('05_Composite_Calibration'!S27,'05_Composite_Calibration'!$S$5:$S$27,1)+(COUNTIF('05_Composite_Calibration'!$S$5:$S$27,'05_Composite_Calibration'!S27)-1)/2) | Q27: =IF(ROW()>=28,"",RANK.EQ(D27,$D$5:$D$27,1)+(COUNTIF($D$5:$D$27,D27)-1)/2) | R27: =MAX($L$5:L27) | S27: =(L27-R27)/R27
A28: ='02_Market_Inputs'!A28 | B28: ='02_Market_Inputs'!C28 | C28: ='02_Market_Inputs'!D28 | D28: =IF(OR(B28=0,C28=0),"",C28/B28-1) | E28: =0 | F28: ='05_Composite_Calibration'!K28 | G28: =IF(F28='01_Model_Config'!$C$16,'01_Model_Config'!$F$16,IF(F28='01_Model_Config'!$C$17,'01_Model_Config'!$F$17,IF(F28='01_Model_Config'!$C$18,'01_Model_Config'!$F$18,IF(F28='01_Model_Config'!$C$19,'01_Model_Config'!$F$19,'01_Model_Config'!$F$20)))) | H28: =1-G28 | I28: =(1+'02_Market_Inputs'!E28/100)^0.25-1 | J28: =G28*E28+H28*I28 | K28: =K27*(1+J28) | L28: =L27*(1+E28) | M28: =MAX($K$5:K28) | N28: =(K28-M28)/M28 | O28: =IF(OR(AND(F28="BUY",E28>0),AND(F28="ACCUMULATE",E28>0),AND(F28="HOLD",ABS(E28)<0.05),AND(F28="REDUCE",E28<0),AND(F28="SELL",E28<0)),1,0) | P28: =IF(ROW()>=28,"",RANK.EQ('05_Composite_Calibration'!S28,'05_Composite_Calibration'!$S$5:$S$27,1)+(COUNTIF('05_Composite_Calibration'!$S$5:$S$27,'05_Composite_Calibration'!S28)-1)/2) | Q28: =IF(ROW()>=28,"",RANK.EQ(D28,$D$5:$D$27,1)+(COUNTIF($D$5:$D$27,D28)-1)/2) | R28: =MAX($L$5:L28) | S28: =(L28-R28)/R28
A30: FORMULA PERFORMANCE SUMMARY
A31: Metric | B31: Strategy / Signal | C31: Benchmark | D31: Spread | E31: Formula Definition
A32: Cumulative Total Return | B32: =(K28-'01_Model_Config'!$B$35)/'01_Model_Config'!$B$35 | C32: =(L28-'01_Model_Config'!$B$35)/'01_Model_Config'!$B$35 | D32: =B32-C32 | E32: Ending NAV / Initial NAV − 1
A33: Compound Annual Growth Rate | B33: =(K28/'01_Model_Config'!$B$35)^('01_Model_Config'!$B$34/23)-1 | C33: =(L28/'01_Model_Config'!$B$35)^('01_Model_Config'!$B$34/23)-1 | D33: =B33-C33 | E33: (Ending NAV / Initial NAV)^(4/23) − 1
A34: Maximum Drawdown | B34: =MIN(N5:N28) | C34: =MIN(S5:S28) | D34: =B34-C34 | E34: Minimum running-peak drawdown
A35: Annualized Volatility | B35: =STDEV.S(J5:J27)*SQRT('01_Model_Config'!$B$34) | C35: =STDEV.S(E5:E27)*SQRT('01_Model_Config'!$B$34) | D35: =B35-C35 | E35: Sample σ quarterly × √4
A36: Sharpe Ratio | B36: =(B33-'01_Model_Config'!$B$36)/B35 | C36: =(C33-'01_Model_Config'!$B$36)/C35 | D36: =B36-C36 | E36: (CAGR − Rf) / annualized volatility
A37: Spearman Rank IC | B37: =CORREL(P5:P27,Q5:Q27) | C37: =CORREL('05_Composite_Calibration'!D5:D27,D5:D27) | D37: =B37-C37 | E37: Pearson correlation of average ranks = Spearman ρ
A38: Directional Hit Rate | B38: =AVERAGE(O5:O27) | C38: ="N/A" | D38: ="N/A" | E38: Mean of formula hit flags

Sheet 11_Data_Audit_Backfill
A1: DATA PROVENANCE, BACKFILL & RECONCILIATION REGISTER
A2: Institutional audit trail for each point-in-time data stream and formula-control convention
A4: Data Stream | B4: Coverage | C4: Point-in-Time Rule | D4: Methodology | E4: Traceable Source
A5: VN-Index decision close | B5: 24/24 | C5: Quarter t uses last close of t−1 | D5: 2021-Q1 seed = 2020-12-31 close 1,103.87; subsequent values lag committed quarter-end closes once | E5: data/scores/vnindex_quarterly_close.json + HOSE 2020-12-31 seed
A6: Vietnam sovereign curve | B6: 24/24 | C6: Backward as-of merge | D6: Nelson-Siegel fitted 1Y/10Y curve and spread | E6: VN_Bond_Yield_pipeline / fitted_curve_ns_full.json
A7: Broad money M2 | B7: 24/24 | C7: Latest published year as of decision date | D7: ADB KIDB FM2_PTX_PS.VIE plus GSO 2025 update | E7: data/external/m2_credit_adb_gso.csv
A8: Foreign and ETF flows | B8: 24/24 | C8: Quarter-to-date at t−1 | D8: VNDirect HOSE flow history with published market-cap splice | E8: data/scores/vnindex_quarterly_flows.json
A9: ADTV liquidity | B9: 24/24 | C9: ADTV(t−1)/ADTV(t−2)−1 | D9: No forward volume observations | E9: data/scores/vnindex_quarterly_adtv.json
A10: Valuation Z-scores | B10: 20/24; neutral fallback in 2021 | C10: 252-session history available at t−1 | D10: P/E, P/B and EYG rolling Z-scores; no interpolation | E10: data/scores/vnindex_quarterly_market_data.json
A11: Econometric / ML outputs | B11: 24/24 | C11: Training sample ends at as-of date | D11: MLR HAC, VAR/Granger and 8-fold expanding WFV | E11: output/exports/score_*.json
A12: Formula reconciliation | B12: 24/24 | C12: Prior quarters only | D12: Rounded pillars and weighted legs reproduce production scorer; v2 calibration uses STDEV.S with σ-floor, z winsorisation and distance guardrail | E12: verify_workbook_accuracy.py

Sheet 12_Methodology_EN
A1: VN-INDEX QUANTITATIVE MODEL — METHODOLOGY & INTERPRETATION
A2: English guide | scope, point-in-time discipline, architecture, calibration, validation and audit
A4: LIVE SNAPSHOT — FORMULA-LINKED TO THE EXECUTIVE DASHBOARD
A5: Latest quarter | B5: ='00_Executive_Dashboard'!A6
A6: Calibrated action | B6: ='00_Executive_Dashboard'!B6
A7: Calibrated score | B7: ='00_Executive_Dashboard'!C6
A8: Equity allocation | B8: ='00_Executive_Dashboard'!D6
A9: Raw composite | B9: ='00_Executive_Dashboard'!E6
A12: 1. What the model produces
A13: The output is a quarterly allocation-regime score and an associated portfolio action. It is NOT a forecast of returns and NOT a probability of a market crash. It is a disciplined decision aid, not investment advice.
A15: 2. Data and point-in-time discipline
A16: Inputs use VN-Index OHLCV, HOSE market capitalization, VNDirect api-finfo v4 foreign flows for STOCK_HOSE and ETF_HOSE, ADTV, a Nelson-Siegel fitted Vietnam government-bond yield curve, and M2 from ADB KIDB (SBV source) joined to GSO releases.
A17: Each quarter uses only information available at its decision date. If a required source fails, publication stops; the model does not silently substitute fabricated or default data.
A19: 3. Six-pillar architecture
A20: Macro & Monetary 25%; Global & Intermarket 20%; Valuation & Leverage 20%; Econometric Models 15%; Machine Learning 10%; Market Structure 10%. The weighted legs sum to the raw composite.
A22: 4. Calibration v2
A23: After four initial quarters that retain the raw score, calibration uses prior history only: z = (raw − prior_mean) / max(prior_std, min_std); z is winsorised at ±z_cap; calibrated = center + z_scale × z; the result is clipped to [clip_low, clip_high] and constrained to max_dist_from_raw from the raw score.
A24: SCORE_CALIBRATION parameters are center 50, z_scale 15, min_history 4, min_std 5.0, z_cap 3.0, max_dist_from_raw 25.0, and clip 0–100. The min_std floor prevents unstable small-sample dispersion from magnifying z; z_cap limits outlier leverage; max_dist_from_raw prevents the action signal from moving implausibly far from the raw evidence. These v2 safeguards address the 2022-Q2 collapse to 0.00.
A26: 5. Action bands
A27: 80–100 BUY (85–100% equities); 65–79.99 ACCUMULATE (70–85%); 50–64.99 HOLD (40–60%); 35–49.99 REDUCE (20–40%); 0–34.99 SELL (0–20%).
... A36: Start at sheet 00, trace its formulas to sheet 05, then follow raw composite links through sheets 04, 03 and 02. Confirm parameters on sheet 01, model evidence on sheets 06–09, backtest formulas on sheet 10, and provenance on sheet 11. The yellow cells are formulas; verify_workbook_accuracy.py independently evaluates and reconciles them.

Sheet 13_Phuong_Phap_Luan_VN
A1: MÔ HÌNH ĐỊNH LƯỢNG VN-INDEX — PHƯƠNG PHÁP & CÁCH DIỄN GIẢI
A2: Hướng dẫn tiếng Việt | phạm vi, kỷ luật point-in-time, kiến trúc, hiệu chỉnh, kiểm định và kiểm toán
A4: ẢNH CHỤP TRỰC TIẾP — LIÊN KẾT BẰNG CÔNG THỨC TỚI DASHBOARD
A5: Quý mới nhất | B5: ='00_Executive_Dashboard'!A6
A6: Hành động hiệu chỉnh | B6: ='00_Executive_Dashboard'!B6
A7: Điểm hiệu chỉnh | B7: ='00_Executive_Dashboard'!C6
A8: Tỷ trọng cổ phiếu | B8: ='00_Executive_Dashboard'!D6
A9: Điểm tổng hợp thô | B9: ='00_Executive_Dashboard'!E6
A12: 1. Mô hình cho ra cái gì
A13: Đầu ra là điểm thế trận phân bổ theo quý và hành động danh mục tương ứng. Đây KHÔNG phải dự báo lợi suất và KHÔNG phải xác suất thị trường sụp đổ. Mô hình là công cụ hỗ trợ quyết định có kỷ luật, không phải khuyến nghị đầu tư.
A15: 2. Dữ liệu và kỷ luật point-in-time
A16: Đầu vào gồm OHLCV VN-Index, vốn hóa HOSE, dòng vốn ngoại VNDirect api-finfo v4 cho STOCK_HOSE và ETF_HOSE, ADTV, đường cong lợi suất TPCP Việt Nam khớp Nelson-Siegel, cùng M2 từ ADB KIDB (nguồn SBV) nối với công bố GSO.
A17: Mỗi quý chỉ dùng thông tin đã có tại ngày ra quyết định. Nếu nguồn bắt buộc gặp lỗi, hệ thống dừng công bố; mô hình không âm thầm thay bằng dữ liệu bịa đặt hoặc giá trị mặc định.
A19: 3. Kiến trúc sáu trụ cột
A20: Vĩ mô & Tiền tệ 25%; Toàn cầu & Liên thị trường 20%; Định giá & Đòn bẩy 20%; Mô hình Kinh tế lượng 15%; Học máy 10%; Cấu trúc Thị trường 10%. Các phần có trọng số cộng thành điểm tổng hợp thô.
A22: 4. Hiệu chỉnh v2
A23: Bốn quý đầu giữ nguyên điểm thô. Sau đó chỉ dùng lịch sử trước quý hiện tại: z = (raw − prior_mean) / max(prior_std, min_std); winsorise z tại ±z_cap; calibrated = center + z_scale × z; cắt trong [clip_low, clip_high] và ràng buộc khoảng cách so với điểm thô bởi max_dist_from_raw.
A24: Tham số SCORE_CALIBRATION: center 50, z_scale 15, min_history 4, min_std 5.0, z_cap 3.0, max_dist_from_raw 25.0, clip 0–100. Sàn min_std ngăn độ phân tán mẫu nhỏ làm phóng đại z; z_cap hạn chế sức chi phối của ngoại lệ; max_dist_from_raw ngăn tín hiệu hành động lệch phi lý khỏi bằng chứng thô. Ba chốt v2 này xử lý sự cố 2022-Q2 tụt về 0.00.
A26: 5. Dải hành động
A27: 80–100 BUY (85–100% cổ phiếu); 65–79.99 ACCUMULATE (70–85%); 50–64.99 HOLD (40–60%); 35–49.99 REDUCE (20–40%); 0–34.99 SELL (0–20%).
... A36: Bắt đầu ở sheet 00, lần theo công thức tới sheet 05, rồi lần điểm tổng hợp thô qua các sheet 04, 03 và 02. Đối chiếu tham số ở sheet 01, bằng chứng mô hình ở sheet 06–09, công thức backtest ở sheet 10 và nguồn gốc dữ liệu ở sheet 11. Ô màu vàng là công thức; verify_workbook_accuracy.py đánh giá độc lập và đối soát chúng.
